fourbit_subtractor/fourbit_subtractor.v

module fourbit_subtractor(Diff, Borr, input1, input2, input3);

output [3:0] Diff;
output Borr;
input [3:0] input1, input2;
wire [2:0] carrybetween;
input input3;

fulladder_behavioral fs1 (.sumfa(Diff[0]), .carryfa(carrybetween[0]), .input1fa(input1[0]), .input2fa(~input2[0]), .input3fa(1'b1));
fulladder_behavioral fs2 (.sumfa(Diff[1]), .carryfa(carrybetween[1]), .input1fa(input1[1]), .input2fa(~input2[1]), .input3fa(carrybetween[0]));
fulladder_behavioral fs3 (.sumfa(Diff[2]), .carryfa(carrybetween[2]), .input1fa(input1[2]), .input2fa(~input2[2]), .input3fa(carrybetween[1]));
fulladder_behavioral fs4 (.sumfa(Diff[3]), .carryfa(Borr), .input1fa(input1[3]), .input2fa(~input2[3]), .input3fa(carrybetween[2]));


endmodule


module fulladder_behavioral(sumfa, carryfa, input1fa, input2fa, input3fa);

  input input1fa , input2fa, input3fa;
  output reg sumfa , carryfa;

  //Behavioral

  always @(*)
    begin
      sumfa = input1fa  ^ input2fa ^ input3fa;
      carryfa = (input1fa & input2fa) | (input2fa & input3fa) | (input1fa & input3fa);
    end


endmodule


module fourbit_subtractor_test;

  //inputs
  reg [3:0]input1;
  reg [3:0]input2;
  reg input3;

  //outputs
  wire [3:0]Diff;
  wire Borr;

  //instantiat unit under test
  fourbit_subtractor ha ( .Diff(Diff), .Borr(Borr), .input1(input1), .input2(input2), .input3(input3));

  initial begin
    input1 = 4'b0000;
    input2 = 4'b0000;
    input3 = 0;
  end
  
  always #1 input2 = input2 + 1'b1;
  always #2 input1 = input1 + 1'b1;

  initial begin
    $dumpfile("fourbit_subtractor.vcd");
    $dumpvars(0, fourbit_subtractor_test);
    $monitor("time=%g,Diff =%b,Borr =%b,a=%b,b=%b,c=%b", $time, Diff, Borr, input1, input2, input3);
  end
  initial #100 $finish; 

endmodule

fourbit_subtractor/fourbit_subtractor.vcd
$date
	Fri Jan 06 20:48:07 2023
$end
$version
	Icarus Verilog
$end
$timescale
	1s
$end
$scope module fourbit_subtractor_test $end
$var wire 4 ! Diff [3:0] $end
$var wire 1 " Borr $end
$var reg 4 # input1 [3:0] $end
$var reg 4 $ input2 [3:0] $end
$var reg 1 % input3 $end
$scope module ha $end
$var wire 4 & input1 [3:0] $end
$var wire 4 ' input2 [3:0] $end
$var wire 1 % input3 $end
$var wire 3 ( carrybetween [2:0] $end
$var wire 4 ) Diff [3:0] $end
$var wire 1 " Borr $end
$scope module fs1 $end
$var wire 1 * input1fa $end
$var wire 1 + input2fa $end
$var wire 1 , input3fa $end
$var reg 1 - carryfa $end
$var reg 1 . sumfa $end
$upscope $end
$scope module fs2 $end
$var wire 1 / input1fa $end
$var wire 1 0 input2fa $end
$var wire 1 1 input3fa $end
$var reg 1 2 carryfa $end
$var reg 1 3 sumfa $end
$upscope $end
$scope module fs3 $end
$var wire 1 4 input1fa $end
$var wire 1 5 input2fa $end
$var wire 1 6 input3fa $end
$var reg 1 7 carryfa $end
$var reg 1 8 sumfa $end
$upscope $end
$scope module fs4 $end
$var wire 1 9 input1fa $end
$var wire 1 : input2fa $end
$var wire 1 ; input3fa $end
$var reg 1 " carryfa $end
$var reg 1 < sumfa $end
$upscope $end
$upscope $end
$upscope $end
$enddefinitions $end
$comment Show the parameter values. $end
$dumpall
$end
#0
$dumpvars
0<
1;
1:
09
08
17
16
15
04
03
12
11
10
0/
0.
1-
1,
1+
0*
b0 )
b111 (
b0 '
b0 &
0%
b0 $
b0 #
1"
b0 !
$end
#1
0"
1<
0;
07
18
06
02
13
01
b0 (
0-
b1111 !
b1111 )
1.
0+
b1 $
b1 '
#2
11
1+
00
b1 (
1-
b1111 !
b1111 )
1.
1*
b10 $
b10 '
b1 #
b1 &
#3
b1110 !
b1110 )
0.
0+
b11 $
b11 '
#4
11
16
1+
10
05
1-
0.
b11 (
12
b1110 !
b1110 )
13
0*
1/
b100 $
b100 '
b10 #
b10 &
#5
03
01
b10 (
0-
b1101 !
b1101 )
1.
0+
b101 $
b101 '
#6
11
1+
00
b11 (
1-
b1101 !
b1101 )
1.
1*
b110 $
b110 '
b11 #
b11 &
#7
b1100 !
b1100 )
0.
0+
b111 $
b111 '
#8
11
16
1;
1+
10
15
0:
1-
0.
12
03
b111 (
17
b1100 !
b1100 )
18
0*
0/
14
b1000 $
b1000 '
b100 #
b100 &
#9
08
06
02
13
01
b100 (
0-
b1011 !
b1011 )
1.
0+
b1001 $
b1001 '
#10
11
1+
00
b101 (
1-
b1011 !
b1011 )
1.
1*
b1010 $
b1010 '
b101 #
b101 &
#11
b1010 !
b1010 )
0.
0+
b1011 $
b1011 '
#12
11
16
1+
10
05
1-
0.
b111 (
12
b1010 !
b1010 )
13
0*
1/
b1100 $
b1100 '
b110 #
b110 &
#13
03
01
b110 (
0-
b1001 !
b1001 )
1.
0+
b1101 $
b1101 '
#14
11
1+
00
b111 (
1-
b1001 !
b1001 )
1.
1*
b1110 $
b1110 '
b111 #
b111 &
#15
b1000 !
b1000 )
0.
0+
b1111 $
b1111 '
#16
11
16
1;
1+
10
15
1:
1-
0.
12
03
b111 (
17
08
1"
b1000 !
b1000 )
1<
0*
0/
04
19
b0 $
b0 '
b1000 #
b1000 &
#17
0<
0;
07
18
06
02
13
01
b0 (
0-
b111 !
b111 )
1.
0+
b1 $
b1 '
#18
11
1+
00
b1 (
1-
b111 !
b111 )
1.
1*
b10 $
b10 '
b1001 #
b1001 &
#19
b110 !
b110 )
0.
0+
b11 $
b11 '
#20
11
16
1+
10
05
1-
0.
b11 (
12
b110 !
b110 )
13
0*
1/
b100 $
b100 '
b1010 #
b1010 &
#21
03
01
b10 (
0-
b101 !
b101 )
1.
0+
b101 $
b101 '
#22
11
1+
00
b11 (
1-
b101 !
b101 )
1.
1*
b110 $
b110 '
b1011 #
b1011 &
#23
b100 !
b100 )
0.
0+
b111 $
b111 '
#24
11
16
1;
1+
10
15
0:
1-
0.
12
03
b111 (
17
b100 !
b100 )
18
0*
0/
14
b1000 $
b1000 '
b1100 #
b1100 &
#25
08
06
02
13
01
b100 (
0-
b11 !
b11 )
1.
0+
b1001 $
b1001 '
#26
11
1+
00
b101 (
1-
b11 !
b11 )
1.
1*
b1010 $
b1010 '
b1101 #
b1101 &
#27
b10 !
b10 )
0.
0+
b1011 $
b1011 '
#28
11
16
1+
10
05
1-
0.
b111 (
12
b10 !
b10 )
13
0*
1/
b1100 $
b1100 '
b1110 #
b1110 &
#29
03
01
b110 (
0-
b1 !
b1 )
1.
0+
b1101 $
b1101 '
#30
11
1+
00
b111 (
1-
b1 !
b1 )
1.
1*
b1110 $
b1110 '
b1111 #
b1111 &
#31
b0 !
b0 )
0.
0+
b1111 $
b1111 '
#32
11
16
1;
1+
10
15
1:
1-
0.
12
03
b111 (
17
08
1"
b0 !
b0 )
0<
0*
0/
04
09
b0 $
b0 '
b0 #
b0 &
#33
0"
1<
0;
07
18
06
02
13
01
b0 (
0-
b1111 !
b1111 )
1.
0+
b1 $
b1 '
#34
11
1+
00
b1 (
1-
b1111 !
b1111 )
1.
1*
b10 $
b10 '
b1 #
b1 &
#35
b1110 !
b1110 )
0.
0+
b11 $
b11 '
#36
11
16
1+
10
05
1-
0.
b11 (
12
b1110 !
b1110 )
13
0*
1/
b100 $
b100 '
b10 #
b10 &
#37
03
01
b10 (
0-
b1101 !
b1101 )
1.
0+
b101 $
b101 '
#38
11
1+
00
b11 (
1-
b1101 !
b1101 )
1.
1*
b110 $
b110 '
b11 #
b11 &
#39
b1100 !
b1100 )
0.
0+
b111 $
b111 '
#40
11
16
1;
1+
10
15
0:
1-
0.
12
03
b111 (
17
b1100 !
b1100 )
18
0*
0/
14
b1000 $
b1000 '
b100 #
b100 &
#41
08
06
02
13
01
b100 (
0-
b1011 !
b1011 )
1.
0+
b1001 $
b1001 '
#42
11
1+
00
b101 (
1-
b1011 !
b1011 )
1.
1*
b1010 $
b1010 '
b101 #
b101 &
#43
b1010 !
b1010 )
0.
0+
b1011 $
b1011 '
#44
11
16
1+
10
05
1-
0.
b111 (
12
b1010 !
b1010 )
13
0*
1/
b1100 $
b1100 '
b110 #
b110 &
#45
03
01
b110 (
0-
b1001 !
b1001 )
1.
0+
b1101 $
b1101 '
#46
11
1+
00
b111 (
1-
b1001 !
b1001 )
1.
1*
b1110 $
b1110 '
b111 #
b111 &
#47
b1000 !
b1000 )
0.
0+
b1111 $
b1111 '
#48
11
16
1;
1+
10
15
1:
1-
0.
12
03
b111 (
17
08
1"
b1000 !
b1000 )
1<
0*
0/
04
19
b0 $
b0 '
b1000 #
b1000 &
#49
0<
0;
07
18
06
02
13
01
b0 (
0-
b111 !
b111 )
1.
0+
b1 $
b1 '
#50
11
1+
00
b1 (
1-
b111 !
b111 )
1.
1*
b10 $
b10 '
b1001 #
b1001 &
#51
b110 !
b110 )
0.
0+
b11 $
b11 '
#52
11
16
1+
10
05
1-
0.
b11 (
12
b110 !
b110 )
13
0*
1/
b100 $
b100 '
b1010 #
b1010 &
#53
03
01
b10 (
0-
b101 !
b101 )
1.
0+
b101 $
b101 '
#54
11
1+
00
b11 (
1-
b101 !
b101 )
1.
1*
b110 $
b110 '
b1011 #
b1011 &
#55
b100 !
b100 )
0.
0+
b111 $
b111 '
#56
11
16
1;
1+
10
15
0:
1-
0.
12
03
b111 (
17
b100 !
b100 )
18
0*
0/
14
b1000 $
b1000 '
b1100 #
b1100 &
#57
08
06
02
13
01
b100 (
0-
b11 !
b11 )
1.
0+
b1001 $
b1001 '
#58
11
1+
00
b101 (
1-
b11 !
b11 )
1.
1*
b1010 $
b1010 '
b1101 #
b1101 &
#59
b10 !
b10 )
0.
0+
b1011 $
b1011 '
#60
11
16
1+
10
05
1-
0.
b111 (
12
b10 !
b10 )
13
0*
1/
b1100 $
b1100 '
b1110 #
b1110 &
#61
03
01
b110 (
0-
b1 !
b1 )
1.
0+
b1101 $
b1101 '
#62
11
1+
00
b111 (
1-
b1 !
b1 )
1.
1*
b1110 $
b1110 '
b1111 #
b1111 &
#63
b0 !
b0 )
0.
0+
b1111 $
b1111 '
#64
11
16
1;
1+
10
15
1:
1-
0.
12
03
b111 (
17
08
1"
b0 !
b0 )
0<
0*
0/
04
09
b0 $
b0 '
b0 #
b0 &
#65
0"
1<
0;
07
18
06
02
13
01
b0 (
0-
b1111 !
b1111 )
1.
0+
b1 $
b1 '
#66
11
1+
00
b1 (
1-
b1111 !
b1111 )
1.
1*
b10 $
b10 '
b1 #
b1 &
#67
b1110 !
b1110 )
0.
0+
b11 $
b11 '
#68
11
16
1+
10
05
1-
0.
b11 (
12
b1110 !
b1110 )
13
0*
1/
b100 $
b100 '
b10 #
b10 &
#69
03
01
b10 (
0-
b1101 !
b1101 )
1.
0+
b101 $
b101 '
#70
11
1+
00
b11 (
1-
b1101 !
b1101 )
1.
1*
b110 $
b110 '
b11 #
b11 &
#71
b1100 !
b1100 )
0.
0+
b111 $
b111 '
#72
11
16
1;
1+
10
15
0:
1-
0.
12
03
b111 (
17
b1100 !
b1100 )
18
0*
0/
14
b1000 $
b1000 '
b100 #
b100 &
#73
08
06
02
13
01
b100 (
0-
b1011 !
b1011 )
1.
0+
b1001 $
b1001 '
#74
11
1+
00
b101 (
1-
b1011 !
b1011 )
1.
1*
b1010 $
b1010 '
b101 #
b101 &
#75
b1010 !
b1010 )
0.
0+
b1011 $
b1011 '
#76
11
16
1+
10
05
1-
0.
b111 (
12
b1010 !
b1010 )
13
0*
1/
b1100 $
b1100 '
b110 #
b110 &
#77
03
01
b110 (
0-
b1001 !
b1001 )
1.
0+
b1101 $
b1101 '
#78
11
1+
00
b111 (
1-
b1001 !
b1001 )
1.
1*
b1110 $
b1110 '
b111 #
b111 &
#79
b1000 !
b1000 )
0.
0+
b1111 $
b1111 '
#80
11
16
1;
1+
10
15
1:
1-
0.
12
03
b111 (
17
08
1"
b1000 !
b1000 )
1<
0*
0/
04
19
b0 $
b0 '
b1000 #
b1000 &
#81
0<
0;
07
18
06
02
13
01
b0 (
0-
b111 !
b111 )
1.
0+
b1 $
b1 '
#82
11
1+
00
b1 (
1-
b111 !
b111 )
1.
1*
b10 $
b10 '
b1001 #
b1001 &
#83
b110 !
b110 )
0.
0+
b11 $
b11 '
#84
11
16
1+
10
05
1-
0.
b11 (
12
b110 !
b110 )
13
0*
1/
b100 $
b100 '
b1010 #
b1010 &
#85
03
01
b10 (
0-
b101 !
b101 )
1.
0+
b101 $
b101 '
#86
11
1+
00
b11 (
1-
b101 !
b101 )
1.
1*
b110 $
b110 '
b1011 #
b1011 &
#87
b100 !
b100 )
0.
0+
b111 $
b111 '
#88
11
16
1;
1+
10
15
0:
1-
0.
12
03
b111 (
17
b100 !
b100 )
18
0*
0/
14
b1000 $
b1000 '
b1100 #
b1100 &
#89
08
06
02
13
01
b100 (
0-
b11 !
b11 )
1.
0+
b1001 $
b1001 '
#90
11
1+
00
b101 (
1-
b11 !
b11 )
1.
1*
b1010 $
b1010 '
b1101 #
b1101 &
#91
b10 !
b10 )
0.
0+
b1011 $
b1011 '
#92
11
16
1+
10
05
1-
0.
b111 (
12
b10 !
b10 )
13
0*
1/
b1100 $
b1100 '
b1110 #
b1110 &
#93
03
01
b110 (
0-
b1 !
b1 )
1.
0+
b1101 $
b1101 '
#94
11
1+
00
b111 (
1-
b1 !
b1 )
1.
1*
b1110 $
b1110 '
b1111 #
b1111 &
#95
b0 !
b0 )
0.
0+
b1111 $
b1111 '
#96
11
16
1;
1+
10
15
1:
1-
0.
12
03
b111 (
17
08
1"
b0 !
b0 )
0<
0*
0/
04
09
b0 $
b0 '
b0 #
b0 &
#97
0"
1<
0;
07
18
06
02
13
01
b0 (
0-
b1111 !
b1111 )
1.
0+
b1 $
b1 '
#98
11
1+
00
b1 (
1-
b1111 !
b1111 )
1.
1*
b10 $
b10 '
b1 #
b1 &
#99
b1110 !
b1110 )
0.
0+
b11 $
b11 '
#100
11
16
1+
10
05
1-
0.
b11 (
12
b1110 !
b1110 )
13
0*
1/
b100 $
b100 '
b10 #
b10 &
