demultiplexer_1to8/demultiplexer_1to8.v
`timescale 1ns/1ps

module demultiplexer_1to8(out, input1, select);


output [7:0]out;

input input1;
input [2:0]select;

wire [5:0] interconnections;

demultiplexer_1to2 dm1t21(.out(interconnections[1:0]), .input1(input1), .select(select[0]));

demultiplexer_1to2 dm1t22(.out(interconnections[3:2]), .input1(interconnections[0]), .select(select[1]));
demultiplexer_1to2 dm1t23(.out(interconnections[5:4]), .input1(interconnections[1]), .select(select[1]));

demultiplexer_1to2 dm1t24(.out(out[1:0]), .input1(interconnections[2]), .select(select[2]));
demultiplexer_1to2 dm1t25(.out(out[3:2]), .input1(interconnections[3]), .select(select[2]));
demultiplexer_1to2 dm1t26(.out(out[5:4]), .input1(interconnections[4]), .select(select[2]));
demultiplexer_1to2 dm1t27(.out(out[7:6]), .input1(interconnections[5]), .select(select[2]));


endmodule

module demultiplexer_1to2(out, input1, select);


output [1:0]out;

input input1, select;

assign out[0] = ~(select) & input1;
assign out[1] = (select) & input1;

endmodule


module demultiplexer_1to8_test;

  //inputs
  reg input1;
  reg [2:0]select;

  //outputs
  wire [7:0]out;

  //instantiat unit under test
  demultiplexer_1to8 mp(.out(out), .input1(input1), .select(select));

  initial begin
  
    select = 3'b000;
    input1 = 1'b0;
  
  end

    always #1  select = select + 1'b1;
    always #8  input1 = input1 + 1'b1;


  initial begin
    $dumpfile("demultiplexer_1to8.vcd");
    $dumpvars(0, demultiplexer_1to8_test);
    $monitor("time = %g, out = %b, input1 = %b, select = %b", $time, out, input1, select);
  end
  initial #32 $finish; 


endmodule

demultiplexer_1to8/demultiplexer_1to8.vcd
$date
	Sat Jan 07 00:17:39 2023
$end
$version
	Icarus Verilog
$end
$timescale
	1ps
$end
$scope module demultiplexer_1to8_test $end
$var wire 8 ! out [7:0] $end
$var reg 1 " input1 $end
$var reg 3 # select [2:0] $end
$scope module mp $end
$var wire 1 " input1 $end
$var wire 3 $ select [2:0] $end
$var wire 8 % out [7:0] $end
$var wire 6 & interconnections [5:0] $end
$scope module dm1t21 $end
$var wire 1 " input1 $end
$var wire 1 ' select $end
$var wire 2 ( out [1:0] $end
$upscope $end
$scope module dm1t22 $end
$var wire 1 ) input1 $end
$var wire 1 * select $end
$var wire 2 + out [1:0] $end
$upscope $end
$scope module dm1t23 $end
$var wire 1 , input1 $end
$var wire 1 - select $end
$var wire 2 . out [1:0] $end
$upscope $end
$scope module dm1t24 $end
$var wire 1 / input1 $end
$var wire 1 0 select $end
$var wire 2 1 out [1:0] $end
$upscope $end
$scope module dm1t25 $end
$var wire 1 2 input1 $end
$var wire 1 3 select $end
$var wire 2 4 out [1:0] $end
$upscope $end
$scope module dm1t26 $end
$var wire 1 5 input1 $end
$var wire 1 6 select $end
$var wire 2 7 out [1:0] $end
$upscope $end
$scope module dm1t27 $end
$var wire 1 8 input1 $end
$var wire 1 9 select $end
$var wire 2 : out [1:0] $end
$upscope $end
$upscope $end
$upscope $end
$enddefinitions $end
$comment Show the parameter values. $end
$dumpall
$end
#0
$dumpvars
b0 :
09
08
b0 7
06
05
b0 4
03
02
b0 1
00
0/
b0 .
0-
0,
b0 +
0*
0)
b0 (
0'
b0 &
b0 %
b0 $
b0 #
0"
b0 !
$end
#1000
1'
b1 #
b1 $
#2000
0'
1*
1-
b10 #
b10 $
#3000
1'
b11 #
b11 $
#4000
0'
0*
0-
10
13
16
19
b100 #
b100 $
#5000
1'
b101 #
b101 $
#6000
0'
1*
1-
b110 #
b110 $
#7000
1'
b111 #
b111 $
#8000
b1 1
1/
b1 +
b1 !
b1 %
b0 7
1)
05
b0 .
0,
0'
0*
0-
00
03
06
09
b101 &
b1 (
b0 #
b0 $
1"
#9000
b0 1
0/
b10000 !
b10000 %
b1 7
b0 +
15
0)
b1 .
1,
b10010 &
b10 (
1'
b1 #
b1 $
#10000
b1 4
12
b10 +
b0 7
1)
05
b100 !
b100 %
b0 :
0,
08
b1 (
b1001 &
b0 .
0'
1*
1-
b10 #
b10 $
#11000
b0 4
02
b1000000 !
b1000000 %
b1 :
b0 +
18
0)
b10 .
1,
b100010 &
b10 (
1'
b11 #
b11 $
#12000
b10 1
1/
b1 +
b0 7
1)
05
0,
08
b1 (
b101 &
b0 .
b10 !
b10 %
b0 :
0'
0*
0-
10
13
16
19
b100 #
b100 $
#13000
b0 1
0/
b100000 !
b100000 %
b10 7
b0 +
15
0)
b1 .
1,
b10010 &
b10 (
1'
b101 #
b101 $
#14000
b10 4
12
b10 +
b0 7
1)
05
b1000 !
b1000 %
b0 :
0,
08
b1 (
b1001 &
b0 .
0'
1*
1-
b110 #
b110 $
#15000
b0 4
02
b10000000 !
b10000000 %
b10 :
b0 +
18
0)
b10 .
1,
b100010 &
b10 (
1'
b111 #
b111 $
#16000
08
b0 .
b0 !
b0 %
b0 :
0,
0'
0*
0-
00
03
06
09
b0 &
b0 (
b0 #
b0 $
0"
#17000
1'
b1 #
b1 $
#18000
0'
1*
1-
b10 #
b10 $
#19000
1'
b11 #
b11 $
#20000
0'
0*
0-
10
13
16
19
b100 #
b100 $
#21000
1'
b101 #
b101 $
#22000
0'
1*
1-
b110 #
b110 $
#23000
1'
b111 #
b111 $
#24000
b1 1
1/
b1 +
b1 !
b1 %
b0 7
1)
05
b0 .
0,
0'
0*
0-
00
03
06
09
b101 &
b1 (
b0 #
b0 $
1"
#25000
b0 1
0/
b10000 !
b10000 %
b1 7
b0 +
15
0)
b1 .
1,
b10010 &
b10 (
1'
b1 #
b1 $
#26000
b1 4
12
b10 +
b0 7
1)
05
b100 !
b100 %
b0 :
0,
08
b1 (
b1001 &
b0 .
0'
1*
1-
b10 #
b10 $
#27000
b0 4
02
b1000000 !
b1000000 %
b1 :
b0 +
18
0)
b10 .
1,
b100010 &
b10 (
1'
b11 #
b11 $
#28000
b10 1
1/
b1 +
b0 7
1)
05
0,
08
b1 (
b101 &
b0 .
b10 !
b10 %
b0 :
0'
0*
0-
10
13
16
19
b100 #
b100 $
#29000
b0 1
0/
b100000 !
b100000 %
b10 7
b0 +
15
0)
b1 .
1,
b10010 &
b10 (
1'
b101 #
b101 $
#30000
b10 4
12
b10 +
b0 7
1)
05
b1000 !
b1000 %
b0 :
0,
08
b1 (
b1001 &
b0 .
0'
1*
1-
b110 #
b110 $
#31000
b0 4
02
b10000000 !
b10000000 %
b10 :
b0 +
18
0)
b10 .
1,
b100010 &
b10 (
1'
b111 #
b111 $
#32000
08
b0 .
b0 !
b0 %
b0 :
0,
0'
0*
0-
00
03
06
09
b0 &
b0 (
b0 #
b0 $
0"
