sr_flipflop/sr_flipflop.v
`timescale 1ns/1ps

module sr_flipflop (Q, Qbar, Set, Reset, Clock, Preset, Clear);

output reg Q, Qbar;

input Set, Reset, Clock, Preset, Clear;

  
  always @(posedge Clock)
    if(Clear == 1'b1)
      begin Q<=1'b0; Qbar<=1'b1; end
    else if (Preset == 1'b1)
      begin Q<=1'b1; Qbar<=1'b0; end
    else
      case ({Set, Reset}) 

        2'b00: begin Q<=Q; Qbar<=Qbar; end 
        2'b01: begin Q<=1'b0; Qbar<=1'b1; end 
        2'b10: begin Q<=1'b1; Qbar<=1'b0; end 
        2'b11: begin Q<=1'bx; Qbar<=1'bx; end 
        
        default: {Q, Qbar} <= 2'bxx; 
      endcase


endmodule


module sr_flipflop_test;

  //inputs
  reg  Set, Reset, Clock, Preset, Clear;


  //outputs
  wire Q, Qbar;

  //instantiat unit under test        
  sr_flipflop srflpflp(.Q(Q), .Qbar(Qbar), .Set(Set), .Reset(Reset), .Clock(Clock), .Preset(Preset), .Clear(Clear));

  initial begin
    
    Set = 0;
    Reset = 0;
    Clock = 0;
    Clear = 1'b1;
    #10 Preset = 1'b1;
    #10 Preset = 1'b0;

  end

  always #2 {Set, Reset} = {Set, Reset} + 1'b1;
  always #1 Clock = ~Clock;
  initial #10 Clear = 1'b0;


  initial begin
    $dumpfile("sr_flipflop.vcd");
    $dumpvars(0, sr_flipflop_test);
    $monitor("time = %g, Q = %b, Qbar = %b,, Set = %b, Reset = %b, Clock = %b, Preset = %b, Clear = %b", $time, Q, Qbar, Set, Reset, Clock, Preset, Clear );
  end
  initial #200 $finish; 


endmodule

sr_flipflop/sr_flipflop.vcd
$date
	Sat Jan 07 10:53:16 2023
$end
$version
	Icarus Verilog
$end
$timescale
	1ps
$end
$scope module sr_flipflop_test $end
$var wire 1 ! Qbar $end
$var wire 1 " Q $end
$var reg 1 # Clear $end
$var reg 1 $ Clock $end
$var reg 1 % Preset $end
$var reg 1 & Reset $end
$var reg 1 ' Set $end
$scope module srflpflp $end
$var wire 1 # Clear $end
$var wire 1 $ Clock $end
$var wire 1 % Preset $end
$var wire 1 & Reset $end
$var wire 1 ' Set $end
$var reg 1 " Q $end
$var reg 1 ! Qbar $end
$upscope $end
$upscope $end
$enddefinitions $end
$comment Show the parameter values. $end
$dumpall
$end
#0
$dumpvars
0'
0&
x%
0$
1#
x"
x!
$end
#1000
1!
0"
1$
#2000
0$
1&
#3000
1$
#4000
0$
1'
0&
#5000
1$
#6000
0$
1&
#7000
1$
#8000
0$
0'
0&
#9000
1$
#10000
0$
1&
0#
1%
#11000
0!
1"
1$
#12000
0$
1'
0&
#13000
1$
#14000
0$
1&
#15000
1$
#16000
0$
0'
0&
#17000
1$
#18000
0$
1&
#19000
1$
#20000
0$
1'
0&
0%
#21000
1$
#22000
0$
1&
#23000
x!
x"
1$
#24000
0$
0'
0&
#25000
1$
#26000
0$
1&
#27000
1!
0"
1$
#28000
0$
1'
0&
#29000
0!
1"
1$
#30000
0$
1&
#31000
x!
x"
1$
#32000
0$
0'
0&
#33000
1$
#34000
0$
1&
#35000
1!
0"
1$
#36000
0$
1'
0&
#37000
0!
1"
1$
#38000
0$
1&
#39000
x!
x"
1$
#40000
0$
0'
0&
#41000
1$
#42000
0$
1&
#43000
1!
0"
1$
#44000
0$
1'
0&
#45000
0!
1"
1$
#46000
0$
1&
#47000
x!
x"
1$
#48000
0$
0'
0&
#49000
1$
#50000
0$
1&
#51000
1!
0"
1$
#52000
0$
1'
0&
#53000
0!
1"
1$
#54000
0$
1&
#55000
x!
x"
1$
#56000
0$
0'
0&
#57000
1$
#58000
0$
1&
#59000
1!
0"
1$
#60000
0$
1'
0&
#61000
0!
1"
1$
#62000
0$
1&
#63000
x!
x"
1$
#64000
0$
0'
0&
#65000
1$
#66000
0$
1&
#67000
1!
0"
1$
#68000
0$
1'
0&
#69000
0!
1"
1$
#70000
0$
1&
#71000
x!
x"
1$
#72000
0$
0'
0&
#73000
1$
#74000
0$
1&
#75000
1!
0"
1$
#76000
0$
1'
0&
#77000
0!
1"
1$
#78000
0$
1&
#79000
x!
x"
1$
#80000
0$
0'
0&
#81000
1$
#82000
0$
1&
#83000
1!
0"
1$
#84000
0$
1'
0&
#85000
0!
1"
1$
#86000
0$
1&
#87000
x!
x"
1$
#88000
0$
0'
0&
#89000
1$
#90000
0$
1&
#91000
1!
0"
1$
#92000
0$
1'
0&
#93000
0!
1"
1$
#94000
0$
1&
#95000
x!
x"
1$
#96000
0$
0'
0&
#97000
1$
#98000
0$
1&
#99000
1!
0"
1$
#100000
0$
1'
0&
#101000
0!
1"
1$
#102000
0$
1&
#103000
x!
x"
1$
#104000
0$
0'
0&
#105000
1$
#106000
0$
1&
#107000
1!
0"
1$
#108000
0$
1'
0&
#109000
0!
1"
1$
#110000
0$
1&
#111000
x!
x"
1$
#112000
0$
0'
0&
#113000
1$
#114000
0$
1&
#115000
1!
0"
1$
#116000
0$
1'
0&
#117000
0!
1"
1$
#118000
0$
1&
#119000
x!
x"
1$
#120000
0$
0'
0&
#121000
1$
#122000
0$
1&
#123000
1!
0"
1$
#124000
0$
1'
0&
#125000
0!
1"
1$
#126000
0$
1&
#127000
x!
x"
1$
#128000
0$
0'
0&
#129000
1$
#130000
0$
1&
#131000
1!
0"
1$
#132000
0$
1'
0&
#133000
0!
1"
1$
#134000
0$
1&
#135000
x!
x"
1$
#136000
0$
0'
0&
#137000
1$
#138000
0$
1&
#139000
1!
0"
1$
#140000
0$
1'
0&
#141000
0!
1"
1$
#142000
0$
1&
#143000
x!
x"
1$
#144000
0$
0'
0&
#145000
1$
#146000
0$
1&
#147000
1!
0"
1$
#148000
0$
1'
0&
#149000
0!
1"
1$
#150000
0$
1&
#151000
x!
x"
1$
#152000
0$
0'
0&
#153000
1$
#154000
0$
1&
#155000
1!
0"
1$
#156000
0$
1'
0&
#157000
0!
1"
1$
#158000
0$
1&
#159000
x!
x"
1$
#160000
0$
0'
0&
#161000
1$
#162000
0$
1&
#163000
1!
0"
1$
#164000
0$
1'
0&
#165000
0!
1"
1$
#166000
0$
1&
#167000
x!
x"
1$
#168000
0$
0'
0&
#169000
1$
#170000
0$
1&
#171000
1!
0"
1$
#172000
0$
1'
0&
#173000
0!
1"
1$
#174000
0$
1&
#175000
x!
x"
1$
#176000
0$
0'
0&
#177000
1$
#178000
0$
1&
#179000
1!
0"
1$
#180000
0$
1'
0&
#181000
0!
1"
1$
#182000
0$
1&
#183000
x!
x"
1$
#184000
0$
0'
0&
#185000
1$
#186000
0$
1&
#187000
1!
0"
1$
#188000
0$
1'
0&
#189000
0!
1"
1$
#190000
0$
1&
#191000
x!
x"
1$
#192000
0$
0'
0&
#193000
1$
#194000
0$
1&
#195000
1!
0"
1$
#196000
0$
1'
0&
#197000
0!
1"
1$
#198000
0$
1&
#199000
x!
x"
1$
#200000
0$
0'
0&
