fourbit_adder/fourbit_adder.v

module fourbit_adder(sum, carry, input1, input2, input3);

output [3:0] sum;
output carry;
wire [2:0]carrybetween;
input [3:0] input1, input2;
input input3;

fulladder_behavioral fa1 (.sumfa(sum[0]), .carryfa(carrybetween[0]), .input1fa(input1[0]), .input2fa(input2[0]), .input3fa(input3));
fulladder_behavioral fa2 (.sumfa(sum[1]), .carryfa(carrybetween[1]), .input1fa(input1[1]), .input2fa(input2[1]), .input3fa(carrybetween[0]));
fulladder_behavioral fa3 (.sumfa(sum[2]), .carryfa(carrybetween[2]), .input1fa(input1[2]), .input2fa(input2[2]), .input3fa(carrybetween[1]));
fulladder_behavioral fa4 (.sumfa(sum[3]), .carryfa(carry), .input1fa(input1[3]), .input2fa(input2[3]), .input3fa(carrybetween[2]));


endmodule


module fulladder_behavioral(sumfa, carryfa, input1fa, input2fa, input3fa);

  input input1fa , input2fa, input3fa;
  output reg sumfa , carryfa;

  //Behavioral

  always @(*)
    begin
      sumfa = input1fa  ^ input2fa ^ input3fa;
      carryfa = (input1fa & input2fa) | (input2fa & input3fa) | (input1fa & input3fa);
    end

endmodule


module fourbit_adder_test;

  //inputs
  reg [3:0]input1;
  reg [3:0]input2;
  reg input3;

  //outputs
  wire [3:0]sum;
  wire carry;

  //instantiat unit under test
  fourbit_adder ha ( .sum(sum), .carry(carry), .input1(input1), .input2(input2), .input3(input3));

  initial begin
    input1 = 4'b0000;
    input2 = 4'b0000;
    input3 = 0;
  end
  
  always #2 input1 = input1 + 1'b1;
  always #1 input2 = input2 + 1'b1;

  initial begin
    $dumpfile("fourbit_adder.vcd");
    $dumpvars(0, fourbit_adder_test);
    $monitor("time=%g,sum =%b,carry =%b,a=%b,b=%b,c=%b", $time, sum, carry, input1, input2, input3);
  end
  initial #100 $finish; 

endmodule

fourbit_adder/fourbit_adder.vcd
$date
	Fri Jan 06 18:28:02 2023
$end
$version
	Icarus Verilog
$end
$timescale
	1s
$end
$scope module fourbit_adder_test $end
$var wire 4 ! sum [3:0] $end
$var wire 1 " carry $end
$var reg 4 # input1 [3:0] $end
$var reg 4 $ input2 [3:0] $end
$var reg 1 % input3 $end
$scope module ha $end
$var wire 4 & input1 [3:0] $end
$var wire 4 ' input2 [3:0] $end
$var wire 1 % input3 $end
$var wire 4 ( sum [3:0] $end
$var wire 3 ) carrybetween [2:0] $end
$var wire 1 " carry $end
$scope module fa1 $end
$var wire 1 * input1fa $end
$var wire 1 + input2fa $end
$var wire 1 % input3fa $end
$var reg 1 , carryfa $end
$var reg 1 - sumfa $end
$upscope $end
$scope module fa2 $end
$var wire 1 . input1fa $end
$var wire 1 / input2fa $end
$var wire 1 0 input3fa $end
$var reg 1 1 carryfa $end
$var reg 1 2 sumfa $end
$upscope $end
$scope module fa3 $end
$var wire 1 3 input1fa $end
$var wire 1 4 input2fa $end
$var wire 1 5 input3fa $end
$var reg 1 6 carryfa $end
$var reg 1 7 sumfa $end
$upscope $end
$scope module fa4 $end
$var wire 1 8 input1fa $end
$var wire 1 9 input2fa $end
$var wire 1 : input3fa $end
$var reg 1 " carryfa $end
$var reg 1 ; sumfa $end
$upscope $end
$upscope $end
$upscope $end
$enddefinitions $end
$comment Show the parameter values. $end
$dumpall
$end
#0
$dumpvars
0;
0:
09
08
07
06
05
04
03
02
01
00
0/
0.
0-
0,
0+
0*
b0 )
b0 (
b0 '
b0 &
0%
b0 $
b0 #
0"
b0 !
$end
#1
b1 !
b1 (
1-
1+
b1 $
b1 '
#2
b11 !
b11 (
12
0+
1/
1*
b10 $
b10 '
b1 #
b1 &
#3
17
15
11
02
10
b11 )
1,
b100 !
b100 (
0-
1+
b11 $
b11 '
#4
05
0;
01
12
0:
00
06
b110 !
b110 (
17
b0 )
0,
0+
0/
14
0*
1.
b100 $
b100 '
b10 #
b10 &
#5
b111 !
b111 (
1-
1+
b101 $
b101 '
#6
1;
1:
16
07
15
b110 )
11
b1001 !
b1001 (
02
0+
1/
1*
b110 $
b110 '
b11 #
b11 &
#7
12
10
b111 )
1,
b1010 !
b1010 (
0-
1+
b111 $
b111 '
#8
0:
02
06
17
00
05
0"
b1100 !
b1100 (
1;
0,
b0 )
01
0+
0/
04
19
0*
0.
13
b1000 $
b1000 '
b100 #
b100 &
#9
b1101 !
b1101 (
1-
1+
b1001 $
b1001 '
#10
b1111 !
b1111 (
12
0+
1/
1*
b1010 $
b1010 '
b101 #
b101 &
#11
1"
0;
1:
16
07
15
11
02
10
b111 )
1,
b0 !
b0 (
0-
1+
b1011 $
b1011 '
#12
05
01
12
00
b10 !
b10 (
07
b100 )
0,
0+
0/
14
0*
1.
b1100 $
b1100 '
b110 #
b110 &
#13
b11 !
b11 (
1-
1+
b1101 $
b1101 '
#14
17
15
b110 )
11
b101 !
b101 (
02
0+
1/
1*
b1110 $
b1110 '
b111 #
b111 &
#15
12
10
b111 )
1,
b110 !
b110 (
0-
1+
b1111 $
b1111 '
#16
02
07
0"
b1000 !
b1000 (
1;
00
05
0:
0,
01
b0 )
06
0+
0/
04
09
0*
0.
03
18
b0 $
b0 '
b1000 #
b1000 &
#17
b1001 !
b1001 (
1-
1+
b1 $
b1 '
#18
b1011 !
b1011 (
12
0+
1/
1*
b10 $
b10 '
b1001 #
b1001 &
#19
17
15
11
02
10
b11 )
1,
b1100 !
b1100 (
0-
1+
b11 $
b11 '
#20
05
0"
1;
01
12
0:
00
06
b1110 !
b1110 (
17
b0 )
0,
0+
0/
14
0*
1.
b100 $
b100 '
b1010 #
b1010 &
#21
b1111 !
b1111 (
1-
1+
b101 $
b101 '
#22
1"
0;
1:
16
07
15
b110 )
11
b1 !
b1 (
02
0+
1/
1*
b110 $
b110 '
b1011 #
b1011 &
#23
12
10
b111 )
1,
b10 !
b10 (
0-
1+
b111 $
b111 '
#24
0:
02
06
17
00
05
b100 !
b100 (
0;
0,
b0 )
01
0+
0/
04
19
0*
0.
13
b1000 $
b1000 '
b1100 #
b1100 &
#25
b101 !
b101 (
1-
1+
b1001 $
b1001 '
#26
b111 !
b111 (
12
0+
1/
1*
b1010 $
b1010 '
b1101 #
b1101 &
#27
1;
1:
16
07
15
11
02
10
b111 )
1,
b1000 !
b1000 (
0-
1+
b1011 $
b1011 '
#28
05
01
12
00
b1010 !
b1010 (
07
b100 )
0,
0+
0/
14
0*
1.
b1100 $
b1100 '
b1110 #
b1110 &
#29
b1011 !
b1011 (
1-
1+
b1101 $
b1101 '
#30
17
15
b110 )
11
b1101 !
b1101 (
02
0+
1/
1*
b1110 $
b1110 '
b1111 #
b1111 &
#31
12
10
b111 )
1,
b1110 !
b1110 (
0-
1+
b1111 $
b1111 '
#32
02
07
b0 !
b0 (
0;
00
05
0:
0,
01
b0 )
06
0"
0+
0/
04
09
0*
0.
03
08
b0 $
b0 '
b0 #
b0 &
#33
b1 !
b1 (
1-
1+
b1 $
b1 '
#34
b11 !
b11 (
12
0+
1/
1*
b10 $
b10 '
b1 #
b1 &
#35
17
15
11
02
10
b11 )
1,
b100 !
b100 (
0-
1+
b11 $
b11 '
#36
05
0;
01
12
0:
00
06
b110 !
b110 (
17
b0 )
0,
0+
0/
14
0*
1.
b100 $
b100 '
b10 #
b10 &
#37
b111 !
b111 (
1-
1+
b101 $
b101 '
#38
1;
1:
16
07
15
b110 )
11
b1001 !
b1001 (
02
0+
1/
1*
b110 $
b110 '
b11 #
b11 &
#39
12
10
b111 )
1,
b1010 !
b1010 (
0-
1+
b111 $
b111 '
#40
0:
02
06
17
00
05
0"
b1100 !
b1100 (
1;
0,
b0 )
01
0+
0/
04
19
0*
0.
13
b1000 $
b1000 '
b100 #
b100 &
#41
b1101 !
b1101 (
1-
1+
b1001 $
b1001 '
#42
b1111 !
b1111 (
12
0+
1/
1*
b1010 $
b1010 '
b101 #
b101 &
#43
1"
0;
1:
16
07
15
11
02
10
b111 )
1,
b0 !
b0 (
0-
1+
b1011 $
b1011 '
#44
05
01
12
00
b10 !
b10 (
07
b100 )
0,
0+
0/
14
0*
1.
b1100 $
b1100 '
b110 #
b110 &
#45
b11 !
b11 (
1-
1+
b1101 $
b1101 '
#46
17
15
b110 )
11
b101 !
b101 (
02
0+
1/
1*
b1110 $
b1110 '
b111 #
b111 &
#47
12
10
b111 )
1,
b110 !
b110 (
0-
1+
b1111 $
b1111 '
#48
02
07
0"
b1000 !
b1000 (
1;
00
05
0:
0,
01
b0 )
06
0+
0/
04
09
0*
0.
03
18
b0 $
b0 '
b1000 #
b1000 &
#49
b1001 !
b1001 (
1-
1+
b1 $
b1 '
#50
b1011 !
b1011 (
12
0+
1/
1*
b10 $
b10 '
b1001 #
b1001 &
#51
17
15
11
02
10
b11 )
1,
b1100 !
b1100 (
0-
1+
b11 $
b11 '
#52
05
0"
1;
01
12
0:
00
06
b1110 !
b1110 (
17
b0 )
0,
0+
0/
14
0*
1.
b100 $
b100 '
b1010 #
b1010 &
#53
b1111 !
b1111 (
1-
1+
b101 $
b101 '
#54
1"
0;
1:
16
07
15
b110 )
11
b1 !
b1 (
02
0+
1/
1*
b110 $
b110 '
b1011 #
b1011 &
#55
12
10
b111 )
1,
b10 !
b10 (
0-
1+
b111 $
b111 '
#56
0:
02
06
17
00
05
b100 !
b100 (
0;
0,
b0 )
01
0+
0/
04
19
0*
0.
13
b1000 $
b1000 '
b1100 #
b1100 &
#57
b101 !
b101 (
1-
1+
b1001 $
b1001 '
#58
b111 !
b111 (
12
0+
1/
1*
b1010 $
b1010 '
b1101 #
b1101 &
#59
1;
1:
16
07
15
11
02
10
b111 )
1,
b1000 !
b1000 (
0-
1+
b1011 $
b1011 '
#60
05
01
12
00
b1010 !
b1010 (
07
b100 )
0,
0+
0/
14
0*
1.
b1100 $
b1100 '
b1110 #
b1110 &
#61
b1011 !
b1011 (
1-
1+
b1101 $
b1101 '
#62
17
15
b110 )
11
b1101 !
b1101 (
02
0+
1/
1*
b1110 $
b1110 '
b1111 #
b1111 &
#63
12
10
b111 )
1,
b1110 !
b1110 (
0-
1+
b1111 $
b1111 '
#64
02
07
b0 !
b0 (
0;
00
05
0:
0,
01
b0 )
06
0"
0+
0/
04
09
0*
0.
03
08
b0 $
b0 '
b0 #
b0 &
#65
b1 !
b1 (
1-
1+
b1 $
b1 '
#66
b11 !
b11 (
12
0+
1/
1*
b10 $
b10 '
b1 #
b1 &
#67
17
15
11
02
10
b11 )
1,
b100 !
b100 (
0-
1+
b11 $
b11 '
#68
05
0;
01
12
0:
00
06
b110 !
b110 (
17
b0 )
0,
0+
0/
14
0*
1.
b100 $
b100 '
b10 #
b10 &
#69
b111 !
b111 (
1-
1+
b101 $
b101 '
#70
1;
1:
16
07
15
b110 )
11
b1001 !
b1001 (
02
0+
1/
1*
b110 $
b110 '
b11 #
b11 &
#71
12
10
b111 )
1,
b1010 !
b1010 (
0-
1+
b111 $
b111 '
#72
0:
02
06
17
00
05
0"
b1100 !
b1100 (
1;
0,
b0 )
01
0+
0/
04
19
0*
0.
13
b1000 $
b1000 '
b100 #
b100 &
#73
b1101 !
b1101 (
1-
1+
b1001 $
b1001 '
#74
b1111 !
b1111 (
12
0+
1/
1*
b1010 $
b1010 '
b101 #
b101 &
#75
1"
0;
1:
16
07
15
11
02
10
b111 )
1,
b0 !
b0 (
0-
1+
b1011 $
b1011 '
#76
05
01
12
00
b10 !
b10 (
07
b100 )
0,
0+
0/
14
0*
1.
b1100 $
b1100 '
b110 #
b110 &
#77
b11 !
b11 (
1-
1+
b1101 $
b1101 '
#78
17
15
b110 )
11
b101 !
b101 (
02
0+
1/
1*
b1110 $
b1110 '
b111 #
b111 &
#79
12
10
b111 )
1,
b110 !
b110 (
0-
1+
b1111 $
b1111 '
#80
02
07
0"
b1000 !
b1000 (
1;
00
05
0:
0,
01
b0 )
06
0+
0/
04
09
0*
0.
03
18
b0 $
b0 '
b1000 #
b1000 &
#81
b1001 !
b1001 (
1-
1+
b1 $
b1 '
#82
b1011 !
b1011 (
12
0+
1/
1*
b10 $
b10 '
b1001 #
b1001 &
#83
17
15
11
02
10
b11 )
1,
b1100 !
b1100 (
0-
1+
b11 $
b11 '
#84
05
0"
1;
01
12
0:
00
06
b1110 !
b1110 (
17
b0 )
0,
0+
0/
14
0*
1.
b100 $
b100 '
b1010 #
b1010 &
#85
b1111 !
b1111 (
1-
1+
b101 $
b101 '
#86
1"
0;
1:
16
07
15
b110 )
11
b1 !
b1 (
02
0+
1/
1*
b110 $
b110 '
b1011 #
b1011 &
#87
12
10
b111 )
1,
b10 !
b10 (
0-
1+
b111 $
b111 '
#88
0:
02
06
17
00
05
b100 !
b100 (
0;
0,
b0 )
01
0+
0/
04
19
0*
0.
13
b1000 $
b1000 '
b1100 #
b1100 &
#89
b101 !
b101 (
1-
1+
b1001 $
b1001 '
#90
b111 !
b111 (
12
0+
1/
1*
b1010 $
b1010 '
b1101 #
b1101 &
#91
1;
1:
16
07
15
11
02
10
b111 )
1,
b1000 !
b1000 (
0-
1+
b1011 $
b1011 '
#92
05
01
12
00
b1010 !
b1010 (
07
b100 )
0,
0+
0/
14
0*
1.
b1100 $
b1100 '
b1110 #
b1110 &
#93
b1011 !
b1011 (
1-
1+
b1101 $
b1101 '
#94
17
15
b110 )
11
b1101 !
b1101 (
02
0+
1/
1*
b1110 $
b1110 '
b1111 #
b1111 &
#95
12
10
b111 )
1,
b1110 !
b1110 (
0-
1+
b1111 $
b1111 '
#96
02
07
b0 !
b0 (
0;
00
05
0:
0,
01
b0 )
06
0"
0+
0/
04
09
0*
0.
03
08
b0 $
b0 '
b0 #
b0 &
#97
b1 !
b1 (
1-
1+
b1 $
b1 '
#98
b11 !
b11 (
12
0+
1/
1*
b10 $
b10 '
b1 #
b1 &
#99
17
15
11
02
10
b11 )
1,
b100 !
b100 (
0-
1+
b11 $
b11 '
#100
05
0;
01
12
0:
00
06
b110 !
b110 (
17
b0 )
0,
0+
0/
14
0*
1.
b100 $
b100 '
b10 #
b10 &
