fullsubtractor_behavioral/fullsubtractor_behavioral.v
module fullsubtractor_behavioral(output reg Diff, Borr, input input1, input2, InBorr);
 
  //Behavioral
  always @(*)
    
    begin
      Diff = input1 ^ input2 ^ InBorr;
      Borr = ((~input1) & input2 ) | (~(input1 ^ input2 ) & InBorr);
    end

endmodule


module fullsubtractor_test;

  //inputs
  reg input1;
  reg input2;
  reg InBorr;

  //outputs
  wire Diff;
  wire Borr;

  //instantiat unit under test
  fullsubtractor_behavioral ha ( .Diff(Diff), .Borr(Borr), .input1(input1), .input2(input2), .InBorr(InBorr));

  initial begin

    {input1, input2, InBorr} = 0;
  end
  
  always #4 input1 = input1 + 1'b1;
  always #2 input2 = input2 + 1'b1;
  always #1 InBorr = InBorr + 1'b1;

  initial begin
    $dumpfile("fullsubtractor_behavioral.vcd");
    $dumpvars(0, fullsubtractor_test);
    $monitor("time=%g,Diff =%b,Borr =%b, input1=%b, input2=%b, InBorra=%b", $time, Diff, Borr, input1, input2, InBorr);
  end
  
  initial #20 $finish; 

endmodule

fullsubtractor_behavioral/fullsubtractor_behavioral.vcd
$date
	Fri Jan 06 16:59:37 2023
$end
$version
	Icarus Verilog
$end
$timescale
	1s
$end
$scope module fullsubtractor_test $end
$var wire 1 ! Diff $end
$var wire 1 " Borr $end
$var reg 1 # InBorr $end
$var reg 1 $ input1 $end
$var reg 1 % input2 $end
$scope module ha $end
$var wire 1 # InBorr $end
$var wire 1 $ input1 $end
$var wire 1 % input2 $end
$var reg 1 " Borr $end
$var reg 1 ! Diff $end
$upscope $end
$upscope $end
$enddefinitions $end
$comment Show the parameter values. $end
$dumpall
$end
#0
$dumpvars
0%
0$
0#
0"
0!
$end
#1
1"
1!
1#
#2
0#
1%
#3
0!
1#
#4
0"
1!
0#
0%
1$
#5
0!
1#
#6
0#
1%
#7
1"
1!
1#
#8
0"
0!
0#
0%
0$
#9
1"
1!
1#
#10
0#
1%
#11
0!
1#
#12
0"
1!
0#
0%
1$
#13
0!
1#
#14
0#
1%
#15
1"
1!
1#
#16
0"
0!
0#
0%
0$
#17
1"
1!
1#
#18
0#
1%
#19
0!
1#
#20
0"
1!
0#
0%
1$
