d_latch/d_latch.v
`timescale 1ns/1ps

module d_latch (Q, Qbar, Clock, input1);

output Q, Qbar;

input Clock, input1;

  
assign Q = ~((Clock & ~input1) | Qbar ) ;
assign Qbar= ~((Clock & input1) | Q ) ;

endmodule


module d_latch_test;

  //inputs
  reg Clock, input1;


  //outputs
  wire Q, Qbar;

  //instantiat unit under test
  d_latch enc(.Q(Q), .Qbar(Qbar), .Clock(Clock), .input1(input1));

  initial begin
     input1 = 1'b1;
     Clock = 1'b1;
     end
  always #6 Clock = Clock + 1'b1;
  initial begin
    

  #1  input1 = 1'b0;
  #1  input1 = 1'b1;
  #1  input1 = 1'b0;
  #1  input1 = 1'b1;
  #1  input1 = 1'b1;
  #1  input1 = 1'b0;
  #1  input1 = 1'b0;
  #1  input1 = 1'b1;
  #1  input1 = 1'b0; 
  #1  input1 = 1'b1; 
  #1  input1 = 1'b0; 
  #1  input1 = 1'b0; 
  #1  input1 = 1'b0; 
  #1  input1 = 1'b0; 
  #1  input1 = 1'b1; 
  #1  input1 = 1'b0; 
  #1  input1 = 1'b0; 
  #1  input1 = 1'b0; 
  #1  input1 = 1'b0; 
  #1  input1 = 1'b1; 
  #1  input1 = 1'b1; 
  #1  input1 = 1'b0; 
  #1  input1 = 1'b1; 
  #1  input1 = 1'b0; 
  #1  input1 = 1'b0; 
  #1  input1 = 1'b0; 
  #1  input1 = 1'b1; 
  #1  input1 = 1'b1; 
  #1  input1 = 1'b1; 
  #1  input1 = 1'b0; 
  #1  input1 = 1'b1; 
  #1  input1 = 1'b0; 
  #1  input1 = 1'b0; 
  #1  input1 = 1'b0; 
  #1  input1 = 1'b0; 
  #1  input1 = 1'b1; 
  #1  input1 = 1'b0; 
  #1  input1 = 1'b0; 
  #1  input1 = 1'b0; 
  #1  input1 = 1'b0; 
  #1  input1 = 1'b1; 
  #1  input1 = 1'b1; 
  end

  initial begin
    $dumpfile("d_latch.vcd");
    $dumpvars(0, d_latch_test);
    $monitor("time = %g, Q = %b, Qbar = %b, input1 = %b, Clock = %b", $time, Q, Qbar, input1, Clock);
  end
  initial #70 $finish; 


endmodule

d_latch/d_latch.vcd
$date
	Sat Jan 07 03:14:27 2023
$end
$version
	Icarus Verilog
$end
$timescale
	1ps
$end
$scope module d_latch_test $end
$var wire 1 ! Qbar $end
$var wire 1 " Q $end
$var reg 1 # Clock $end
$var reg 1 $ input1 $end
$scope module enc $end
$var wire 1 # Clock $end
$var wire 1 " Q $end
$var wire 1 ! Qbar $end
$var wire 1 $ input1 $end
$upscope $end
$upscope $end
$enddefinitions $end
$comment Show the parameter values. $end
$dumpall
$end
#0
$dumpvars
1$
1#
1"
0!
$end
#1000
1!
0"
0$
#2000
1"
0!
1$
#3000
1!
0"
0$
#4000
1"
0!
1$
#6000
0$
0#
#8000
1$
#9000
0$
#10000
1$
#11000
0$
#12000
1!
0"
1#
#15000
1"
0!
1$
#16000
1!
0"
0$
#18000
0#
#20000
1$
#22000
0$
#23000
1$
#24000
0$
1#
#27000
1"
0!
1$
#30000
0$
0#
#31000
1$
#32000
0$
#36000
1"
1$
1#
#37000
1!
0"
0$
#41000
1"
0!
1$
