encoder_8to3/encoder_8to3.v
`timescale 1ns/1ps

module encoder_8to3 (out, input1);

output reg [2:0] out;

input [7:0] input1;

always @ (*)

case (input1)
  8'h01: out = 3'b000;
  8'h02: out = 3'b001;
  8'h04: out = 3'b010;
  8'h08: out = 3'b011;
  8'h10: out = 3'b100;
  8'h20: out = 3'b101;
  8'h40: out = 3'b110;
  8'h80: out = 3'b111;
  default: out = 3'bxxx;
endcase

endmodule


module encoder_8to3_test;

  //inputs
  reg [7:0] input1;

  //outputs
  wire [2:0] out;

  //instantiat unit under test
  encoder_8to3 enc(.out(out), .input1(input1));

  initial begin
  
    input1 = 8'h00;
    #1  input1 = + 8'h01;
    #1  input1 = + 8'h02;
    #1  input1 = + 8'h04;
    #1  input1 = + 8'h08;
    #1  input1 = + 8'h10;
    #1  input1 = + 8'h20;
    #1  input1 = + 8'h40;
    #1  input1 = + 8'h80;
  
  end



  initial begin
    $dumpfile("encoder_8to3.vcd");
    $dumpvars(0, encoder_8to3_test);
    $monitor("time = %g, out = %b, input1 = %b", $time, out, input1);
  end
  initial #32 $finish; 


endmodule

encoder_8to3/encoder_8to3.vcd
$date
	Sat Jan 07 01:27:40 2023
$end
$version
	Icarus Verilog
$end
$timescale
	1ps
$end
$scope module encoder_8to3_test $end
$var wire 3 ! out [2:0] $end
$var reg 8 " input1 [7:0] $end
$scope module enc $end
$var wire 8 # input1 [7:0] $end
$var reg 3 $ out [2:0] $end
$upscope $end
$upscope $end
$enddefinitions $end
$comment Show the parameter values. $end
$dumpall
$end
#0
$dumpvars
bx $
b0 #
b0 "
bx !
$end
#1000
b0 !
b0 $
b1 "
b1 #
#2000
b1 !
b1 $
b10 "
b10 #
#3000
b10 !
b10 $
b100 "
b100 #
#4000
b11 !
b11 $
b1000 "
b1000 #
#5000
b100 !
b100 $
b10000 "
b10000 #
#6000
b101 !
b101 $
b100000 "
b100000 #
#7000
b110 !
b110 $
b1000000 "
b1000000 #
#8000
b111 !
b111 $
b10000000 "
b10000000 #
