demultiplexer_1to2/demultiplexer_1to2.v
module demultiplexer_1to2(out, input1, select);


output [1:0]out;

input input1, select;

assign out[0] = ~(select) & input1;
assign out[1] = (select) & input1;

endmodule


module demultiplexer_1to2_test;

  //inputs
  reg input1;
  reg select;

  //outputs
  wire [1:0]out;

  //instantiat unit under test
  demultiplexer_1to2 mp(.out(out), .input1(input1), .select(select));

  initial begin
  
    select = 1'b0;
    input1 = 1'b1;  
  
  end

    always #2  select = select + 1'b1;
    always #1  input1 = input1 + 1'b1;


  initial begin
    $dumpfile("demultiplexer_1to2.vcd");
    $dumpvars(0, demultiplexer_1to2_test);
    $monitor("time = %g, out = %b, input1 = %b, select = %b", $time, out, input1, select);
  end
  initial #10 $finish; 


endmodule

demultiplexer_1to2/demultiplexer_1to2.vcd
$date
	Fri Jan 06 23:51:07 2023
$end
$version
	Icarus Verilog
$end
$timescale
	1s
$end
$scope module demultiplexer_1to2_test $end
$var wire 2 ! out [1:0] $end
$var reg 1 " input1 $end
$var reg 1 # select $end
$scope module mp $end
$var wire 1 " input1 $end
$var wire 1 # select $end
$var wire 2 $ out [1:0] $end
$upscope $end
$upscope $end
$enddefinitions $end
$comment Show the parameter values. $end
$dumpall
$end
#0
$dumpvars
b1 $
0#
1"
b1 !
$end
#1
b0 !
b0 $
0"
#2
b10 !
b10 $
1"
1#
#3
b0 !
b0 $
0"
#4
b1 !
b1 $
1"
0#
#5
b0 !
b0 $
0"
#6
b10 !
b10 $
1"
1#
#7
b0 !
b0 $
0"
#8
b1 !
b1 $
1"
0#
#9
b0 !
b0 $
0"
#10
b10 !
b10 $
1"
1#
