sixteenbit_adder/sixteenbit_adder.v

module sixteenbit_adder(sum, carry, input1, input2, input3);

output [15:0] sum;
output carry;
wire [14:0]carrybetween;
input [15:0] input1, input2;
input input3;

fulladder_behavioral fa0 (.sumfa(sum[0]), .carryfa(carrybetween[0]), .input1fa(input1[0]), .input2fa(input2[0]), .input3fa(input3));
fulladder_behavioral fa1 (.sumfa(sum[1]), .carryfa(carrybetween[1]),   .input1fa(input1[1]),  .input2fa(input2[1]),   .input3fa(carrybetween[0]));
fulladder_behavioral fa2 (.sumfa(sum[2]), .carryfa(carrybetween[2]),   .input1fa(input1[2]),  .input2fa(input2[2]),   .input3fa(carrybetween[1]));
fulladder_behavioral fa3 (.sumfa(sum[3]), .carryfa(carrybetween[3]),   .input1fa(input1[3]),  .input2fa(input2[3]),   .input3fa(carrybetween[2]));
fulladder_behavioral fa4 (.sumfa(sum[4]), .carryfa(carrybetween[4]),   .input1fa(input1[4]),  .input2fa(input2[4]),   .input3fa(carrybetween[3]));
fulladder_behavioral fa5 (.sumfa(sum[5]), .carryfa(carrybetween[5]),   .input1fa(input1[5]),  .input2fa(input2[5]),   .input3fa(carrybetween[4]));
fulladder_behavioral fa6 (.sumfa(sum[6]), .carryfa(carrybetween[6]),   .input1fa(input1[6]),  .input2fa(input2[6]),   .input3fa(carrybetween[5]));
fulladder_behavioral fa7 (.sumfa(sum[7]), .carryfa(carrybetween[7]),   .input1fa(input1[7]),  .input2fa(input2[7]),   .input3fa(carrybetween[6]));
fulladder_behavioral fa8 (.sumfa(sum[8]), .carryfa(carrybetween[8]),   .input1fa(input1[8]),  .input2fa(input2[8]),   .input3fa(carrybetween[7]));
fulladder_behavioral fa9 (.sumfa(sum[9]), .carryfa(carrybetween[9]),   .input1fa(input1[9]),  .input2fa(input2[9]),   .input3fa(carrybetween[8]));
fulladder_behavioral fa10 (.sumfa(sum[10]),.carryfa(carrybetween[10]),  .input1fa(input1[10]), .input2fa(input2[10]),  .input3fa(carrybetween[9]));
fulladder_behavioral fa11 (.sumfa(sum[11]), .carryfa(carrybetween[11]), .input1fa(input1[11]), .input2fa(input2[11]),  .input3fa(carrybetween[10]));
fulladder_behavioral fa12 (.sumfa(sum[12]), .carryfa(carrybetween[12]), .input1fa(input1[12]), .input2fa(input2[12]),  .input3fa(carrybetween[11]));
fulladder_behavioral fa13 (.sumfa(sum[13]), .carryfa(carrybetween[13]), .input1fa(input1[13]), .input2fa(input2[13]),  .input3fa(carrybetween[12]));
fulladder_behavioral fa14 (.sumfa(sum[14]), .carryfa(carrybetween[14]), .input1fa(input1[14]), .input2fa(input2[14]),  .input3fa(carrybetween[13]));
fulladder_behavioral fa15 (.sumfa(sum[15]), .carryfa(carry), .input1fa(input1[15]), .input2fa(input2[15]), .input3fa(carrybetween[14]));


endmodule


module fulladder_behavioral(sumfa, carryfa, input1fa, input2fa, input3fa);

  input input1fa , input2fa, input3fa;
  output reg sumfa , carryfa;

  //Behavioral

  always @(*)
    begin
      sumfa = input1fa  ^ input2fa ^ input3fa;
      carryfa = (input1fa & input2fa) | (input2fa & input3fa) | (input1fa & input3fa);
    end

endmodule


module sixteenbit_adder_test;

  //inputs
  reg [15:0]input1;
  reg [15:0]input2;
  reg input3;

  //outputs
  wire [15:0]sum;
  wire carry;

  //instantiat unit under test
  sixteenbit_adder ha ( .sum(sum), .carry(carry), .input1(input1), .input2(input2), .input3(input3));

  initial begin
    input1 = 16'b0000000000000000;
    input2 = 16'b0000000000000000;
    input3 = 0;
  end
  
  always #2 input1 = input1 + 1'b1;
  always #1 input2 = input2 + 1'b1;

  initial begin
    $dumpfile("sixteenbit_adder.vcd");
    $dumpvars(0, sixteenbit_adder_test);
    $monitor("time=%g,sum =%b,carry =%b,a=%b,b=%b,c=%b", $time, sum, carry, input1, input2, input3);
  end
  initial #1000 $finish; 

endmodule

sixteenbit_adder/sixteenbit_adder.vcd
$date
	Fri Jan 06 21:08:31 2023
$end
$version
	Icarus Verilog
$end
$timescale
	1s
$end
$scope module sixteenbit_adder_test $end
$var wire 16 ! sum [15:0] $end
$var wire 1 " carry $end
$var reg 16 # input1 [15:0] $end
$var reg 16 $ input2 [15:0] $end
$var reg 1 % input3 $end
$scope module ha $end
$var wire 16 & input1 [15:0] $end
$var wire 16 ' input2 [15:0] $end
$var wire 1 % input3 $end
$var wire 16 ( sum [15:0] $end
$var wire 15 ) carrybetween [14:0] $end
$var wire 1 " carry $end
$scope module fa0 $end
$var wire 1 * input1fa $end
$var wire 1 + input2fa $end
$var wire 1 % input3fa $end
$var reg 1 , carryfa $end
$var reg 1 - sumfa $end
$upscope $end
$scope module fa1 $end
$var wire 1 . input1fa $end
$var wire 1 / input2fa $end
$var wire 1 0 input3fa $end
$var reg 1 1 carryfa $end
$var reg 1 2 sumfa $end
$upscope $end
$scope module fa10 $end
$var wire 1 3 input1fa $end
$var wire 1 4 input2fa $end
$var wire 1 5 input3fa $end
$var reg 1 6 carryfa $end
$var reg 1 7 sumfa $end
$upscope $end
$scope module fa11 $end
$var wire 1 8 input1fa $end
$var wire 1 9 input2fa $end
$var wire 1 : input3fa $end
$var reg 1 ; carryfa $end
$var reg 1 < sumfa $end
$upscope $end
$scope module fa12 $end
$var wire 1 = input1fa $end
$var wire 1 > input2fa $end
$var wire 1 ? input3fa $end
$var reg 1 @ carryfa $end
$var reg 1 A sumfa $end
$upscope $end
$scope module fa13 $end
$var wire 1 B input1fa $end
$var wire 1 C input2fa $end
$var wire 1 D input3fa $end
$var reg 1 E carryfa $end
$var reg 1 F sumfa $end
$upscope $end
$scope module fa14 $end
$var wire 1 G input1fa $end
$var wire 1 H input2fa $end
$var wire 1 I input3fa $end
$var reg 1 J carryfa $end
$var reg 1 K sumfa $end
$upscope $end
$scope module fa15 $end
$var wire 1 L input1fa $end
$var wire 1 M input2fa $end
$var wire 1 N input3fa $end
$var reg 1 " carryfa $end
$var reg 1 O sumfa $end
$upscope $end
$scope module fa2 $end
$var wire 1 P input1fa $end
$var wire 1 Q input2fa $end
$var wire 1 R input3fa $end
$var reg 1 S carryfa $end
$var reg 1 T sumfa $end
$upscope $end
$scope module fa3 $end
$var wire 1 U input1fa $end
$var wire 1 V input2fa $end
$var wire 1 W input3fa $end
$var reg 1 X carryfa $end
$var reg 1 Y sumfa $end
$upscope $end
$scope module fa4 $end
$var wire 1 Z input1fa $end
$var wire 1 [ input2fa $end
$var wire 1 \ input3fa $end
$var reg 1 ] carryfa $end
$var reg 1 ^ sumfa $end
$upscope $end
$scope module fa5 $end
$var wire 1 _ input1fa $end
$var wire 1 ` input2fa $end
$var wire 1 a input3fa $end
$var reg 1 b carryfa $end
$var reg 1 c sumfa $end
$upscope $end
$scope module fa6 $end
$var wire 1 d input1fa $end
$var wire 1 e input2fa $end
$var wire 1 f input3fa $end
$var reg 1 g carryfa $end
$var reg 1 h sumfa $end
$upscope $end
$scope module fa7 $end
$var wire 1 i input1fa $end
$var wire 1 j input2fa $end
$var wire 1 k input3fa $end
$var reg 1 l carryfa $end
$var reg 1 m sumfa $end
$upscope $end
$scope module fa8 $end
$var wire 1 n input1fa $end
$var wire 1 o input2fa $end
$var wire 1 p input3fa $end
$var reg 1 q carryfa $end
$var reg 1 r sumfa $end
$upscope $end
$scope module fa9 $end
$var wire 1 s input1fa $end
$var wire 1 t input2fa $end
$var wire 1 u input3fa $end
$var reg 1 v carryfa $end
$var reg 1 w sumfa $end
$upscope $end
$upscope $end
$upscope $end
$enddefinitions $end
$comment Show the parameter values. $end
$dumpall
$end
#0
$dumpvars
0w
0v
0u
0t
0s
0r
0q
0p
0o
0n
0m
0l
0k
0j
0i
0h
0g
0f
0e
0d
0c
0b
0a
0`
0_
0^
0]
0\
0[
0Z
0Y
0X
0W
0V
0U
0T
0S
0R
0Q
0P
0O
0N
0M
0L
0K
0J
0I
0H
0G
0F
0E
0D
0C
0B
0A
0@
0?
0>
0=
0<
0;
0:
09
08
07
06
05
04
03
02
01
00
0/
0.
0-
0,
0+
0*
b0 )
b0 (
b0 '
b0 &
0%
b0 $
b0 #
0"
b0 !
$end
#1
b1 !
b1 (
1-
1+
b1 $
b1 '
#2
b11 !
b11 (
12
0+
1/
1*
b10 $
b10 '
b1 #
b1 &
#3
1T
1R
11
02
10
b11 )
1,
b100 !
b100 (
0-
1+
b11 $
b11 '
#4
0R
0Y
01
12
0W
00
0S
b110 !
b110 (
1T
b0 )
0,
0+
0/
1Q
0*
1.
b100 $
b100 '
b10 #
b10 &
#5
b111 !
b111 (
1-
1+
b101 $
b101 '
#6
1Y
1W
1S
0T
1R
b110 )
11
b1001 !
b1001 (
02
0+
1/
1*
b110 $
b110 '
b11 #
b11 &
#7
12
10
b111 )
1,
b1010 !
b1010 (
0-
1+
b111 $
b111 '
#8
0W
0^
02
0S
1T
0\
00
0R
0X
b1100 !
b1100 (
1Y
0,
b0 )
01
0+
0/
0Q
1V
0*
0.
1P
b1000 $
b1000 '
b100 #
b100 &
#9
b1101 !
b1101 (
1-
1+
b1001 $
b1001 '
#10
b1111 !
b1111 (
12
0+
1/
1*
b1010 $
b1010 '
b101 #
b101 &
#11
1^
1\
1X
0Y
1W
1S
0T
1R
11
02
10
b1111 )
1,
b10000 !
b10000 (
0-
1+
b1011 $
b1011 '
#12
0R
01
12
00
b10010 !
b10010 (
0T
b1100 )
0,
0+
0/
1Q
0*
1.
b1100 $
b1100 '
b110 #
b110 &
#13
b10011 !
b10011 (
1-
1+
b1101 $
b1101 '
#14
1T
1R
b1110 )
11
b10101 !
b10101 (
02
0+
1/
1*
b1110 $
b1110 '
b111 #
b111 &
#15
12
10
b1111 )
1,
b10110 !
b10110 (
0-
1+
b1111 $
b1111 '
#16
0\
0c
02
0T
0X
1Y
0a
00
0R
0W
0]
b11000 !
b11000 (
1^
0,
01
b0 )
0S
0+
0/
0Q
0V
1[
0*
0.
0P
1U
b10000 $
b10000 '
b1000 #
b1000 &
#17
b11001 !
b11001 (
1-
1+
b10001 $
b10001 '
#18
b11011 !
b11011 (
12
0+
1/
1*
b10010 $
b10010 '
b1001 #
b1001 &
#19
1T
1R
11
02
10
b11 )
1,
b11100 !
b11100 (
0-
1+
b10011 $
b10011 '
#20
0c
0a
0]
1^
0\
0R
0X
1Y
01
12
0W
00
0S
b11110 !
b11110 (
1T
b0 )
0,
0+
0/
1Q
0*
1.
b10100 $
b10100 '
b1010 #
b1010 &
#21
b11111 !
b11111 (
1-
1+
b10101 $
b10101 '
#22
1c
1a
1]
0^
1\
1X
0Y
1W
1S
0T
1R
b11110 )
11
b100001 !
b100001 (
02
0+
1/
1*
b10110 $
b10110 '
b1011 #
b1011 &
#23
12
10
b11111 )
1,
b100010 !
b100010 (
0-
1+
b10111 $
b10111 '
#24
0W
02
0S
1T
00
0R
b100100 !
b100100 (
0Y
0,
b11000 )
01
0+
0/
0Q
1V
0*
0.
1P
b11000 $
b11000 '
b1100 #
b1100 &
#25
b100101 !
b100101 (
1-
1+
b11001 $
b11001 '
#26
b100111 !
b100111 (
12
0+
1/
1*
b11010 $
b11010 '
b1101 #
b1101 &
#27
1Y
1W
1S
0T
1R
11
02
10
b11111 )
1,
b101000 !
b101000 (
0-
1+
b11011 $
b11011 '
#28
0R
01
12
00
b101010 !
b101010 (
0T
b11100 )
0,
0+
0/
1Q
0*
1.
b11100 $
b11100 '
b1110 #
b1110 &
#29
b101011 !
b101011 (
1-
1+
b11101 $
b11101 '
#30
1T
1R
b11110 )
11
b101101 !
b101101 (
02
0+
1/
1*
b11110 $
b11110 '
b1111 #
b1111 &
#31
12
10
b11111 )
1,
b101110 !
b101110 (
0-
1+
b11111 $
b11111 '
#32
0a
0h
02
0T
0Y
0]
1^
0f
00
0R
0W
0\
0b
b110000 !
b110000 (
1c
0,
01
0S
b0 )
0X
0+
0/
0Q
0V
0[
1`
0*
0.
0P
0U
1Z
b100000 $
b100000 '
b10000 #
b10000 &
#33
b110001 !
b110001 (
1-
1+
b100001 $
b100001 '
#34
b110011 !
b110011 (
12
0+
1/
1*
b100010 $
b100010 '
b10001 #
b10001 &
#35
1T
1R
11
02
10
b11 )
1,
b110100 !
b110100 (
0-
1+
b100011 $
b100011 '
#36
0R
0Y
01
12
0W
00
0S
b110110 !
b110110 (
1T
b0 )
0,
0+
0/
1Q
0*
1.
b100100 $
b100100 '
b10010 #
b10010 &
#37
b110111 !
b110111 (
1-
1+
b100101 $
b100101 '
#38
1Y
1W
1S
0T
1R
b110 )
11
b111001 !
b111001 (
02
0+
1/
1*
b100110 $
b100110 '
b10011 #
b10011 &
#39
12
10
b111 )
1,
b111010 !
b111010 (
0-
1+
b100111 $
b100111 '
#40
0h
0f
0b
1c
0a
0W
0]
1^
02
0S
1T
0\
00
0R
0X
b111100 !
b111100 (
1Y
0,
b0 )
01
0+
0/
0Q
1V
0*
0.
1P
b101000 $
b101000 '
b10100 #
b10100 &
#41
b111101 !
b111101 (
1-
1+
b101001 $
b101001 '
#42
b111111 !
b111111 (
12
0+
1/
1*
b101010 $
b101010 '
b10101 #
b10101 &
#43
1h
1f
1b
0c
1a
1]
0^
1\
1X
0Y
1W
1S
0T
1R
11
02
10
b111111 )
1,
b1000000 !
b1000000 (
0-
1+
b101011 $
b101011 '
#44
0R
01
12
00
b1000010 !
b1000010 (
0T
b111100 )
0,
0+
0/
1Q
0*
1.
b101100 $
b101100 '
b10110 #
b10110 &
#45
b1000011 !
b1000011 (
1-
1+
b101101 $
b101101 '
#46
1T
1R
b111110 )
11
b1000101 !
b1000101 (
02
0+
1/
1*
b101110 $
b101110 '
b10111 #
b10111 &
#47
12
10
b111111 )
1,
b1000110 !
b1000110 (
0-
1+
b101111 $
b101111 '
#48
0\
02
0T
0X
1Y
00
0R
0W
b1001000 !
b1001000 (
0^
0,
01
b110000 )
0S
0+
0/
0Q
0V
1[
0*
0.
0P
1U
b110000 $
b110000 '
b11000 #
b11000 &
#49
b1001001 !
b1001001 (
1-
1+
b110001 $
b110001 '
#50
b1001011 !
b1001011 (
12
0+
1/
1*
b110010 $
b110010 '
b11001 #
b11001 &
#51
1T
1R
11
02
10
b110011 )
1,
b1001100 !
b1001100 (
0-
1+
b110011 $
b110011 '
#52
0^
0\
0R
0X
1Y
01
12
0W
00
0S
b1001110 !
b1001110 (
1T
b110000 )
0,
0+
0/
1Q
0*
1.
b110100 $
b110100 '
b11010 #
b11010 &
#53
b1001111 !
b1001111 (
1-
1+
b110101 $
b110101 '
#54
1^
1\
1X
0Y
1W
1S
0T
1R
b111110 )
11
b1010001 !
b1010001 (
02
0+
1/
1*
b110110 $
b110110 '
b11011 #
b11011 &
#55
12
10
b111111 )
1,
b1010010 !
b1010010 (
0-
1+
b110111 $
b110111 '
#56
0W
02
0S
1T
00
0R
b1010100 !
b1010100 (
0Y
0,
b111000 )
01
0+
0/
0Q
1V
0*
0.
1P
b111000 $
b111000 '
b11100 #
b11100 &
#57
b1010101 !
b1010101 (
1-
1+
b111001 $
b111001 '
#58
b1010111 !
b1010111 (
12
0+
1/
1*
b111010 $
b111010 '
b11101 #
b11101 &
#59
1Y
1W
1S
0T
1R
11
02
10
b111111 )
1,
b1011000 !
b1011000 (
0-
1+
b111011 $
b111011 '
#60
0R
01
12
00
b1011010 !
b1011010 (
0T
b111100 )
0,
0+
0/
1Q
0*
1.
b111100 $
b111100 '
b11110 #
b11110 &
#61
b1011011 !
b1011011 (
1-
1+
b111101 $
b111101 '
#62
1T
1R
b111110 )
11
b1011101 !
b1011101 (
02
0+
1/
1*
b111110 $
b111110 '
b11111 #
b11111 &
#63
12
10
b111111 )
1,
b1011110 !
b1011110 (
0-
1+
b111111 $
b111111 '
#64
0f
0m
02
0T
0Y
0^
0b
1c
0k
00
0R
0W
0\
0a
0g
b1100000 !
b1100000 (
1h
0,
01
0S
0X
b0 )
0]
0+
0/
0Q
0V
0[
0`
1e
0*
0.
0P
0U
0Z
1_
b1000000 $
b1000000 '
b100000 #
b100000 &
#65
b1100001 !
b1100001 (
1-
1+
b1000001 $
b1000001 '
#66
b1100011 !
b1100011 (
12
0+
1/
1*
b1000010 $
b1000010 '
b100001 #
b100001 &
#67
1T
1R
11
02
10
b11 )
1,
b1100100 !
b1100100 (
0-
1+
b1000011 $
b1000011 '
#68
0R
0Y
01
12
0W
00
0S
b1100110 !
b1100110 (
1T
b0 )
0,
0+
0/
1Q
0*
1.
b1000100 $
b1000100 '
b100010 #
b100010 &
#69
b1100111 !
b1100111 (
1-
1+
b1000101 $
b1000101 '
#70
1Y
1W
1S
0T
1R
b110 )
11
b1101001 !
b1101001 (
02
0+
1/
1*
b1000110 $
b1000110 '
b100011 #
b100011 &
#71
12
10
b111 )
1,
b1101010 !
b1101010 (
0-
1+
b1000111 $
b1000111 '
#72
0W
0^
02
0S
1T
0\
00
0R
0X
b1101100 !
b1101100 (
1Y
0,
b0 )
01
0+
0/
0Q
1V
0*
0.
1P
b1001000 $
b1001000 '
b100100 #
b100100 &
#73
b1101101 !
b1101101 (
1-
1+
b1001001 $
b1001001 '
#74
b1101111 !
b1101111 (
12
0+
1/
1*
b1001010 $
b1001010 '
b100101 #
b100101 &
#75
1^
1\
1X
0Y
1W
1S
0T
1R
11
02
10
b1111 )
1,
b1110000 !
b1110000 (
0-
1+
b1001011 $
b1001011 '
#76
0R
01
12
00
b1110010 !
b1110010 (
0T
b1100 )
0,
0+
0/
1Q
0*
1.
b1001100 $
b1001100 '
b100110 #
b100110 &
#77
b1110011 !
b1110011 (
1-
1+
b1001101 $
b1001101 '
#78
1T
1R
b1110 )
11
b1110101 !
b1110101 (
02
0+
1/
1*
b1001110 $
b1001110 '
b100111 #
b100111 &
#79
12
10
b1111 )
1,
b1110110 !
b1110110 (
0-
1+
b1001111 $
b1001111 '
#80
0m
0k
0g
1h
0f
0\
0b
1c
02
0T
0X
1Y
0a
00
0R
0W
0]
b1111000 !
b1111000 (
1^
0,
01
b0 )
0S
0+
0/
0Q
0V
1[
0*
0.
0P
1U
b1010000 $
b1010000 '
b101000 #
b101000 &
#81
b1111001 !
b1111001 (
1-
1+
b1010001 $
b1010001 '
#82
b1111011 !
b1111011 (
12
0+
1/
1*
b1010010 $
b1010010 '
b101001 #
b101001 &
#83
1T
1R
11
02
10
b11 )
1,
b1111100 !
b1111100 (
0-
1+
b1010011 $
b1010011 '
#84
0m
0k
0g
1h
0f
0b
1c
0a
0]
1^
0\
0R
0X
1Y
01
12
0W
00
0S
b1111110 !
b1111110 (
1T
b0 )
0,
0+
0/
1Q
0*
1.
b1010100 $
b1010100 '
b101010 #
b101010 &
#85
b1111111 !
b1111111 (
1-
1+
b1010101 $
b1010101 '
#86
1m
1k
1g
0h
1f
1b
0c
1a
1]
0^
1\
1X
0Y
1W
1S
0T
1R
b1111110 )
11
b10000001 !
b10000001 (
02
0+
1/
1*
b1010110 $
b1010110 '
b101011 #
b101011 &
#87
12
10
b1111111 )
1,
b10000010 !
b10000010 (
0-
1+
b1010111 $
b1010111 '
#88
0W
02
0S
1T
00
0R
b10000100 !
b10000100 (
0Y
0,
b1111000 )
01
0+
0/
0Q
1V
0*
0.
1P
b1011000 $
b1011000 '
b101100 #
b101100 &
#89
b10000101 !
b10000101 (
1-
1+
b1011001 $
b1011001 '
#90
b10000111 !
b10000111 (
12
0+
1/
1*
b1011010 $
b1011010 '
b101101 #
b101101 &
#91
1Y
1W
1S
0T
1R
11
02
10
b1111111 )
1,
b10001000 !
b10001000 (
0-
1+
b1011011 $
b1011011 '
#92
0R
01
12
00
b10001010 !
b10001010 (
0T
b1111100 )
0,
0+
0/
1Q
0*
1.
b1011100 $
b1011100 '
b101110 #
b101110 &
#93
b10001011 !
b10001011 (
1-
1+
b1011101 $
b1011101 '
#94
1T
1R
b1111110 )
11
b10001101 !
b10001101 (
02
0+
1/
1*
b1011110 $
b1011110 '
b101111 #
b101111 &
#95
12
10
b1111111 )
1,
b10001110 !
b10001110 (
0-
1+
b1011111 $
b1011111 '
#96
0a
02
0T
0Y
0]
1^
00
0R
0W
0\
b10010000 !
b10010000 (
0c
0,
01
0S
b1100000 )
0X
0+
0/
0Q
0V
0[
1`
0*
0.
0P
0U
1Z
b1100000 $
b1100000 '
b110000 #
b110000 &
#97
b10010001 !
b10010001 (
1-
1+
b1100001 $
b1100001 '
#98
b10010011 !
b10010011 (
12
0+
1/
1*
b1100010 $
b1100010 '
b110001 #
b110001 &
#99
1T
1R
11
02
10
b1100011 )
1,
b10010100 !
b10010100 (
0-
1+
b1100011 $
b1100011 '
#100
0R
0Y
01
12
0W
00
0S
b10010110 !
b10010110 (
1T
b1100000 )
0,
0+
0/
1Q
0*
1.
b1100100 $
b1100100 '
b110010 #
b110010 &
#101
b10010111 !
b10010111 (
1-
1+
b1100101 $
b1100101 '
#102
1Y
1W
1S
0T
1R
b1100110 )
11
b10011001 !
b10011001 (
02
0+
1/
1*
b1100110 $
b1100110 '
b110011 #
b110011 &
#103
12
10
b1100111 )
1,
b10011010 !
b10011010 (
0-
1+
b1100111 $
b1100111 '
#104
0c
0a
0W
0]
1^
02
0S
1T
0\
00
0R
0X
b10011100 !
b10011100 (
1Y
0,
b1100000 )
01
0+
0/
0Q
1V
0*
0.
1P
b1101000 $
b1101000 '
b110100 #
b110100 &
#105
b10011101 !
b10011101 (
1-
1+
b1101001 $
b1101001 '
#106
b10011111 !
b10011111 (
12
0+
1/
1*
b1101010 $
b1101010 '
b110101 #
b110101 &
#107
1c
1a
1]
0^
1\
1X
0Y
1W
1S
0T
1R
11
02
10
b1111111 )
1,
b10100000 !
b10100000 (
0-
1+
b1101011 $
b1101011 '
#108
0R
01
12
00
b10100010 !
b10100010 (
0T
b1111100 )
0,
0+
0/
1Q
0*
1.
b1101100 $
b1101100 '
b110110 #
b110110 &
#109
b10100011 !
b10100011 (
1-
1+
b1101101 $
b1101101 '
#110
1T
1R
b1111110 )
11
b10100101 !
b10100101 (
02
0+
1/
1*
b1101110 $
b1101110 '
b110111 #
b110111 &
#111
12
10
b1111111 )
1,
b10100110 !
b10100110 (
0-
1+
b1101111 $
b1101111 '
#112
0\
02
0T
0X
1Y
00
0R
0W
b10101000 !
b10101000 (
0^
0,
01
b1110000 )
0S
0+
0/
0Q
0V
1[
0*
0.
0P
1U
b1110000 $
b1110000 '
b111000 #
b111000 &
#113
b10101001 !
b10101001 (
1-
1+
b1110001 $
b1110001 '
#114
b10101011 !
b10101011 (
12
0+
1/
1*
b1110010 $
b1110010 '
b111001 #
b111001 &
#115
1T
1R
11
02
10
b1110011 )
1,
b10101100 !
b10101100 (
0-
1+
b1110011 $
b1110011 '
#116
0^
0\
0R
0X
1Y
01
12
0W
00
0S
b10101110 !
b10101110 (
1T
b1110000 )
0,
0+
0/
1Q
0*
1.
b1110100 $
b1110100 '
b111010 #
b111010 &
#117
b10101111 !
b10101111 (
1-
1+
b1110101 $
b1110101 '
#118
1^
1\
1X
0Y
1W
1S
0T
1R
b1111110 )
11
b10110001 !
b10110001 (
02
0+
1/
1*
b1110110 $
b1110110 '
b111011 #
b111011 &
#119
12
10
b1111111 )
1,
b10110010 !
b10110010 (
0-
1+
b1110111 $
b1110111 '
#120
0W
02
0S
1T
00
0R
b10110100 !
b10110100 (
0Y
0,
b1111000 )
01
0+
0/
0Q
1V
0*
0.
1P
b1111000 $
b1111000 '
b111100 #
b111100 &
#121
b10110101 !
b10110101 (
1-
1+
b1111001 $
b1111001 '
#122
b10110111 !
b10110111 (
12
0+
1/
1*
b1111010 $
b1111010 '
b111101 #
b111101 &
#123
1Y
1W
1S
0T
1R
11
02
10
b1111111 )
1,
b10111000 !
b10111000 (
0-
1+
b1111011 $
b1111011 '
#124
0R
01
12
00
b10111010 !
b10111010 (
0T
b1111100 )
0,
0+
0/
1Q
0*
1.
b1111100 $
b1111100 '
b111110 #
b111110 &
#125
b10111011 !
b10111011 (
1-
1+
b1111101 $
b1111101 '
#126
1T
1R
b1111110 )
11
b10111101 !
b10111101 (
02
0+
1/
1*
b1111110 $
b1111110 '
b111111 #
b111111 &
#127
12
10
b1111111 )
1,
b10111110 !
b10111110 (
0-
1+
b1111111 $
b1111111 '
#128
0k
0r
02
0T
0Y
0^
0c
0g
1h
0p
00
0R
0W
0\
0a
0f
0l
b11000000 !
b11000000 (
1m
0,
01
0S
0X
0]
b0 )
0b
0+
0/
0Q
0V
0[
0`
0e
1j
0*
0.
0P
0U
0Z
0_
1d
b10000000 $
b10000000 '
b1000000 #
b1000000 &
#129
b11000001 !
b11000001 (
1-
1+
b10000001 $
b10000001 '
#130
b11000011 !
b11000011 (
12
0+
1/
1*
b10000010 $
b10000010 '
b1000001 #
b1000001 &
#131
1T
1R
11
02
10
b11 )
1,
b11000100 !
b11000100 (
0-
1+
b10000011 $
b10000011 '
#132
0R
0Y
01
12
0W
00
0S
b11000110 !
b11000110 (
1T
b0 )
0,
0+
0/
1Q
0*
1.
b10000100 $
b10000100 '
b1000010 #
b1000010 &
#133
b11000111 !
b11000111 (
1-
1+
b10000101 $
b10000101 '
#134
1Y
1W
1S
0T
1R
b110 )
11
b11001001 !
b11001001 (
02
0+
1/
1*
b10000110 $
b10000110 '
b1000011 #
b1000011 &
#135
12
10
b111 )
1,
b11001010 !
b11001010 (
0-
1+
b10000111 $
b10000111 '
#136
0W
0^
02
0S
1T
0\
00
0R
0X
b11001100 !
b11001100 (
1Y
0,
b0 )
01
0+
0/
0Q
1V
0*
0.
1P
b10001000 $
b10001000 '
b1000100 #
b1000100 &
#137
b11001101 !
b11001101 (
1-
1+
b10001001 $
b10001001 '
#138
b11001111 !
b11001111 (
12
0+
1/
1*
b10001010 $
b10001010 '
b1000101 #
b1000101 &
#139
1^
1\
1X
0Y
1W
1S
0T
1R
11
02
10
b1111 )
1,
b11010000 !
b11010000 (
0-
1+
b10001011 $
b10001011 '
#140
0R
01
12
00
b11010010 !
b11010010 (
0T
b1100 )
0,
0+
0/
1Q
0*
1.
b10001100 $
b10001100 '
b1000110 #
b1000110 &
#141
b11010011 !
b11010011 (
1-
1+
b10001101 $
b10001101 '
#142
1T
1R
b1110 )
11
b11010101 !
b11010101 (
02
0+
1/
1*
b10001110 $
b10001110 '
b1000111 #
b1000111 &
#143
12
10
b1111 )
1,
b11010110 !
b11010110 (
0-
1+
b10001111 $
b10001111 '
#144
0\
0c
02
0T
0X
1Y
0a
00
0R
0W
0]
b11011000 !
b11011000 (
1^
0,
01
b0 )
0S
0+
0/
0Q
0V
1[
0*
0.
0P
1U
b10010000 $
b10010000 '
b1001000 #
b1001000 &
#145
b11011001 !
b11011001 (
1-
1+
b10010001 $
b10010001 '
#146
b11011011 !
b11011011 (
12
0+
1/
1*
b10010010 $
b10010010 '
b1001001 #
b1001001 &
#147
1T
1R
11
02
10
b11 )
1,
b11011100 !
b11011100 (
0-
1+
b10010011 $
b10010011 '
#148
0c
0a
0]
1^
0\
0R
0X
1Y
01
12
0W
00
0S
b11011110 !
b11011110 (
1T
b0 )
0,
0+
0/
1Q
0*
1.
b10010100 $
b10010100 '
b1001010 #
b1001010 &
#149
b11011111 !
b11011111 (
1-
1+
b10010101 $
b10010101 '
#150
1c
1a
1]
0^
1\
1X
0Y
1W
1S
0T
1R
b11110 )
11
b11100001 !
b11100001 (
02
0+
1/
1*
b10010110 $
b10010110 '
b1001011 #
b1001011 &
#151
12
10
b11111 )
1,
b11100010 !
b11100010 (
0-
1+
b10010111 $
b10010111 '
#152
0W
02
0S
1T
00
0R
b11100100 !
b11100100 (
0Y
0,
b11000 )
01
0+
0/
0Q
1V
0*
0.
1P
b10011000 $
b10011000 '
b1001100 #
b1001100 &
#153
b11100101 !
b11100101 (
1-
1+
b10011001 $
b10011001 '
#154
b11100111 !
b11100111 (
12
0+
1/
1*
b10011010 $
b10011010 '
b1001101 #
b1001101 &
#155
1Y
1W
1S
0T
1R
11
02
10
b11111 )
1,
b11101000 !
b11101000 (
0-
1+
b10011011 $
b10011011 '
#156
0R
01
12
00
b11101010 !
b11101010 (
0T
b11100 )
0,
0+
0/
1Q
0*
1.
b10011100 $
b10011100 '
b1001110 #
b1001110 &
#157
b11101011 !
b11101011 (
1-
1+
b10011101 $
b10011101 '
#158
1T
1R
b11110 )
11
b11101101 !
b11101101 (
02
0+
1/
1*
b10011110 $
b10011110 '
b1001111 #
b1001111 &
#159
12
10
b11111 )
1,
b11101110 !
b11101110 (
0-
1+
b10011111 $
b10011111 '
#160
0r
0p
0l
1m
0k
0a
0g
1h
02
0T
0Y
0]
1^
0f
00
0R
0W
0\
0b
b11110000 !
b11110000 (
1c
0,
01
0S
b0 )
0X
0+
0/
0Q
0V
0[
1`
0*
0.
0P
0U
1Z
b10100000 $
b10100000 '
b1010000 #
b1010000 &
#161
b11110001 !
b11110001 (
1-
1+
b10100001 $
b10100001 '
#162
b11110011 !
b11110011 (
12
0+
1/
1*
b10100010 $
b10100010 '
b1010001 #
b1010001 &
#163
1T
1R
11
02
10
b11 )
1,
b11110100 !
b11110100 (
0-
1+
b10100011 $
b10100011 '
#164
0R
0Y
01
12
0W
00
0S
b11110110 !
b11110110 (
1T
b0 )
0,
0+
0/
1Q
0*
1.
b10100100 $
b10100100 '
b1010010 #
b1010010 &
#165
b11110111 !
b11110111 (
1-
1+
b10100101 $
b10100101 '
#166
1Y
1W
1S
0T
1R
b110 )
11
b11111001 !
b11111001 (
02
0+
1/
1*
b10100110 $
b10100110 '
b1010011 #
b1010011 &
#167
12
10
b111 )
1,
b11111010 !
b11111010 (
0-
1+
b10100111 $
b10100111 '
