fulladder_instantiation/fulladder_instantiation.v
module fulladder_instantiation(sum, carry, input1, input2, input3);

  input input1 , input2, input3;
  output sum, carry;

  wire sum1, carry2;

  halfadder_dataflow ha1 ( .sumha(sum1), .carryha(carry1), .input1ha(input1), .input2ha(input2));
  halfadder_dataflow ha2 ( .sumha(sum), .carryha(carry2), .input1ha(sum1), .input2ha(input3));
  or (carry, carry2, carry1);

endmodule







module halfadder_dataflow(sumha,carryha,input1ha,input2ha);
  input input1ha , input2ha;
  output sumha , carryha;
  //Dataflow
  assign sumha =  input1ha ^ input2ha;
  assign carryha =  input1ha & input2ha;
endmodule



module fulladder_instantiation_test;

  //inputs
  reg input1;
  reg input2;
  reg input3;

  //outputs
  wire sum;
  wire carry;

  //instantiat unit under test
  fulladder_instantiation ha ( .sum(sum), .carry(carry), .input1(input1), .input2(input2), .input3(input3));

  initial begin

    input1 =1'b1;
    input2 =1'b0;
    input3 = 1'b1;
  
  end
  
  always #2 input1 = input1 + 1'b1;
  always #3 input2 = input2 + 1'b1;
  always #4 input3 = input3 + 1'b1;

  initial begin
    $dumpfile("fulladder_instantiation.vcd");
    $dumpvars(0, fulladder_instantiation_test);
    $monitor("time=%g,sum =%b,carry =%b,a=%b,b=%b,c=%b", $time, sum, carry, input1, input2, input3);
  end
  initial #100 $finish; 

endmodule

fulladder_instantiation/fulladder_instantiation.vcd
$date
	Sat Jan 07 08:26:50 2023
$end
$version
	Icarus Verilog
$end
$timescale
	1s
$end
$scope module fulladder_instantiation_test $end
$var wire 1 ! sum $end
$var wire 1 " carry $end
$var reg 1 # input1 $end
$var reg 1 $ input2 $end
$var reg 1 % input3 $end
$scope module ha $end
$var wire 1 " carry $end
$var wire 1 # input1 $end
$var wire 1 $ input2 $end
$var wire 1 % input3 $end
$var wire 1 & sum1 $end
$var wire 1 ! sum $end
$var wire 1 ' carry2 $end
$var wire 1 ( carry1 $end
$scope module ha1 $end
$var wire 1 ( carryha $end
$var wire 1 # input1ha $end
$var wire 1 $ input2ha $end
$var wire 1 & sumha $end
$upscope $end
$scope module ha2 $end
$var wire 1 ' carryha $end
$var wire 1 & input1ha $end
$var wire 1 % input2ha $end
$var wire 1 ! sumha $end
$upscope $end
$upscope $end
$upscope $end
$enddefinitions $end
$comment Show the parameter values. $end
$dumpall
$end
#0
$dumpvars
0(
1'
1&
1%
0$
1#
1"
0!
$end
#2
0"
1!
0'
0&
0#
#3
1"
0!
1'
1&
1$
#4
0&
1(
0!
0'
1#
0%
#6
0"
0(
0#
0$
#8
1"
1'
1&
0!
1#
1%
#9
1!
0'
0&
1(
1$
#10
0!
1'
1"
1&
0(
0#
#12
0"
1!
0'
1#
0$
0%
#14
0!
0&
0#
#15
1!
1&
1$
#16
1"
0&
1(
1!
0'
1#
1%
#18
0"
0(
0#
0$
#20
1&
1!
1#
0%
#21
0!
1"
0&
1(
1$
#22
1!
0"
1&
0(
0#
#24
1"
0!
1'
1#
0$
1%
#26
0"
1!
0'
0&
0#
#27
1"
0!
1'
1&
1$
#28
0&
1(
0!
0'
1#
0%
#30
0"
0(
0#
0$
#32
1"
1'
1&
0!
1#
1%
#33
1!
0'
0&
1(
1$
#34
0!
1'
1"
1&
0(
0#
#36
0"
1!
0'
1#
0$
0%
#38
0!
0&
0#
#39
1!
1&
1$
#40
1"
0&
1(
1!
0'
1#
1%
#42
0"
0(
0#
0$
#44
1&
1!
1#
0%
#45
0!
1"
0&
1(
1$
#46
1!
0"
1&
0(
0#
#48
1"
0!
1'
1#
0$
1%
#50
0"
1!
0'
0&
0#
#51
1"
0!
1'
1&
1$
#52
0&
1(
0!
0'
1#
0%
#54
0"
0(
0#
0$
#56
1"
1'
1&
0!
1#
1%
#57
1!
0'
0&
1(
1$
#58
0!
1'
1"
1&
0(
0#
#60
0"
1!
0'
1#
0$
0%
#62
0!
0&
0#
#63
1!
1&
1$
#64
1"
0&
1(
1!
0'
1#
1%
#66
0"
0(
0#
0$
#68
1&
1!
1#
0%
#69
0!
1"
0&
1(
1$
#70
1!
0"
1&
0(
0#
#72
1"
0!
1'
1#
0$
1%
#74
0"
1!
0'
0&
0#
#75
1"
0!
1'
1&
1$
#76
0&
1(
0!
0'
1#
0%
#78
0"
0(
0#
0$
#80
1"
1'
1&
0!
1#
1%
#81
1!
0'
0&
1(
1$
#82
0!
1'
1"
1&
0(
0#
#84
0"
1!
0'
1#
0$
0%
#86
0!
0&
0#
#87
1!
1&
1$
#88
1"
0&
1(
1!
0'
1#
1%
#90
0"
0(
0#
0$
#92
1&
1!
1#
0%
#93
0!
1"
0&
1(
1$
#94
1!
0"
1&
0(
0#
#96
1"
0!
1'
1#
0$
1%
#98
0"
1!
0'
0&
0#
#99
1"
0!
1'
1&
1$
#100
0&
1(
0!
0'
1#
0%
